Workbook
Name _centreImpot: "CENTRE DES IMPOTS DE "
Name _dAn: " 2025"
Name _dDeb: " 01/01/2025"
Name _dFin: " 31/12/2025"
Name _Duree: "Durée (en mois) 12"
Name _ExerClos: "Exercice clos le 31/12/2025"
Name _ExerClot: " 31/12/2017"
Name _ExerFin: " 31/12/2025"
Name _ExerFin1: " 31/12/2024"
Name _insae: " "
Name _Mois: 12
Name _nbMois: 12
Name _nCompletPays: "REPUBLIQUE DU BENIN"
Name _nSo: "Cecotra"
Name _Pays: "REPUBLIQUE DU BENIN"
Name _regCom: "RB/ABC/18 B 2310"
Name _sigle: " "
Name _soAdr: " "
Name _soAg1: " "
Name _soAg2: " "
Name _soId: " 3201810353457"
Name _soNom: "Cecotra"
Name _soNumFisc: " 3201810353457"
Name _soSigle: " "
Name _sTabExer: "Tableau financiers au 31/12/2025"
Name _Ville: "CENTRE DES IMPÔTS DE COTONOU"
Name numFisc: " 3201810353457"
Name Print_Area: 'FICHE R3 '!$A$1:$F$36
Name Print_Area: 'NOTE 15A'!$A$1:$H$36
Name Print_Area: 'NOTE 30'!$A$1:$D$41
Name Print_Area: 'NOTE 3E'!$A$1:$C$39
Name Print_Area: 'NOTE 4'!$A$1:$G$62
Name Print_Area: 'NOTE 5'!$A$1:$E$58
Name tauxImpot: 0

Sheet PAGE DE GARDE
A6: REPUBLIQUE DU BENIN
A8: DIRECTION :
B12: CENTRE DE DEPOT DE : CIME ATL
C16: ETATS FINANCIERS NORMALISES
C17: SYSTÈME COMPTABLE OHADA(SYSCOHADA)
D20: EXERCICE CLOS LE : | G20: =_ExerClos -> Exercice clos le 31/12/2025
D23: DESIGNATION DE L'ENTITE
B25: DENOMINATION SOCIALE : | E25: =_soNom -> Cecotra
A26: (ou nom et prénoms de l'exploitant)
B30: SIGLE USUEL :
B32: ADRESSE COMPLETE :
B34: N° D'IDENTIFICATION FISCALE : | E34: =_soId -> 3201810353457
E37: SYSTEME NORMAL
B40: Documents déposés | G40: Réservé à la Direction Générale des Impôts
G41: Date de dépôt
B42: Fiche d'identification et renseignements divers | E42: X
B43: Bilan | E43: X
B44: Compte de résultat | E44: X
B45: Tableau des flux et trésorerie | E45: X | G45: Nom de l'agent de la DGI ayant réceptionné le dépôt
B46: Notes annexées | E46: X
B48: Nombre de pages déposées par exemplaire | G48: Signature de l'agent et cachet du service
B49: Nombre d'exemplaires déposés

Sheet FICHE R1 
B5: Dénomination sociale de l'entité:
B6: =_soNom -> Cecotra | AC6: Sigle usuel :
B7: Adresse :
B8: N° d'identification fiscale : | K8: =_soId -> 3201810353457 | W8: =_ExerClos -> Exercice clos le 31/12/2025 | AN8: =_Duree -> Durée (en mois) 12
B10: ZA | G10: EXERCICE COMPTABLE: | Z10: DU: | AB10: 1er janvier | AJ10: AU | AN10: 31 décembre
B12: ZB | G12: DATE D'ARRETE EFFECTIF DES COMPTES | W12: 31/12/2025
B14: ZC | G14: EXERCICE PRECEDENT CLOS LE: | W14: 31/12/2024 | AB14: DUREE EXERCICE PRECEDENT EN MOIS: | AQ14: 12
B16: ZD | E16: ABC | J16: RB/ABC/18 B 2310 | AB16: 3201810353457
G17: Greffe | J17: N° Registre du commerce | AC17: N° Répertoire des entités
B19: ZE | G19: 18666421 | P19: 14735
G20: N° de caisse sociale | P20: N° Code Importateur | AJ20: Code activité principale
B22: ZF
R23: Désignation de l'entité | AN23: Sigle
B25: ZG
G26: N° de téléphone | Q26: email | AB26: Code | AE26: Bote postale | AN26: Ville
B28: ZH | G28: ILOT 1842 M/KPACOSSOU CODJO TANKPE AB-CLAVI
G29: Adresse géographique complète (Immeuble, rue, quartier, ville, pays)
G30: import-export
B31: ZI
I32: Désignation précise de l'activité principale exercée par l'entité
G34: AKODA ALIDOU ASSOCIER GERANT Tél 61218199
G35: Nom, adresse et qualité de la personne à contacter en cas de demande d'informations complémentaires
G37: Ernest Cyrille A. SOUROU
G38: Nom du professionnel salarié de l'entité ou
G39: Nom, adresse et téléhone du cabinet comptable ou du professionnel INSCRIT A L'ORDRE NATIONAL
G40: DES EXPERTS COMPTABLES ET DES COMPTABLES AGREES ayant établi les états financiers
H45: Visa de l'Expert comptable agrée
AM49: Non | AP49: Oui
AG51: Etats financiers approuvés par l'Assemeblée Générale (cocher la case)
G53: AKODA ALIDOU ASSOCIER GERANT
H54: Nom du sigantaire des états financiers | AB54: Banque | AK54: Numéro de compte
G56: Directeur général
H57: Nom du sigantaire des états financiers | AB57: BIIC | AK57: 208254601
G59: 46081
H60: Date de signature
H66: Signature

Sheet FICHE R2 
B5: Désignation entité : | J5: CECOTRA | AB5: Exercice clos le : | AH5: 46022
B6: Numéro d'identification : | K6: =_soId -> 3201810353457 | AB6: Durée | AH6: 12
W9: Contrôle de l'entité (cocher la case)
B10: ZK | D10: Forme juridique (1) : | R10: 0 | S10: 2 | W10: ZQ | X10: Entité sous contrôle public
B12: ZL | D12: Régime fiscal (1) : | R12: 0 | S12: 2 | W12: ZR | X12: Entité sous contrôle privé national | AJ12: X
B14: ZM | D14: Pays du siège social (1) : | R14: 0 | S14: 1 | W14: ZS | X14: Entité sous contrôle privé étranger
B16: ZN | D16: Nombre d'établissements dans le pays : | R16: 0 | S16: 1
B18: ZO | D18: Nombre d'établissements hors du pays pour | R18: 0 | S18: 0
D19: lesquels une comptabilité distincte est tenue :
B21: ZP | D21: Première année d'exercice dans le pays : | R21: 2 | S21: 0 | T21: 1 | U21: 8
B24: ACTIVITE DE L'ENTITE
B26: Désignation de l'activité (2) | Q26: Code nomenclature | Y26: Chiffre d'affaires HT | AH26: % activité
Q27: d'activité (1) | Y27: (CA HT) | AH27: dans le CA
AH28: HT
Y30: 983417641 | AH30: 1
B40: Divers
Q42: TOTAL | Y42: =SUM(Y30:Y40) -> 983417641 | AH42: 100
B45: (1) NOTE 36
B46: (2) Lister de manière précise les activités dans l'ordre décroissant du C. A. HT, ou de la valeur ajoutée (V. A.).

Sheet FICHE R3 
B6: =_soNom -> Cecotra | F6: =_ExerClos -> Exercice clos le 31/12/2025
B7: =_soId -> 3201810353457 | F7: =_Duree -> Durée (en mois) 12
B9: DIRIGEANTS (1)
B11: Nom | C11: Prénoms | D11: Qualité | E11: N° identification fiscale | F11: Adresse (BP, ville, pays)
B12: AKODA | C12: ALIDOU | D12: Gérant | E12: 3201810353457 | F12: Calavi Tankpe
B19: (1) Dirigeants = Président Directeur Général, Directeur Général, Administrateur Général, Gérant, Autres.
B22: MEMBRES DU CONSEIL D'ADMINISTRATION
B24: Nom | C24: Prénoms | D24: Qualité | E24: Adresse (BP, ville, pays)

Sheet FICHE R4
A3: =_soNom -> Cecotra | C3: =_ExerClos -> Exercice clos le 31/12/2025
A4: =_soId -> 3201810353457 | C4: =_Duree -> Durée (en mois) 12
A6: NOTES | B6: INTITULES | C6: A | D6: N/A
A7: NOTE 1 | B7: DETTES GARANTIES PAR DES SURETTES REELLES | D7: x
A8: NOTE 2 | B8: INFORMATIONS OBLIGTOIRES | C8: x
A9: NOTE 3A | B9: IMMOBILISATION BRUTE | D9: x
A10: NOTE 3B | B10: BIENS PRIS EN LOCATION ACQUISITION | C10: x
A11: NOTE 3C | B11: IMMOBILISATIONS : AMORTISSEMENTS | C11: x
A12: NOTE 3D | B12: IMMOBLISATIONS : PLUS-VALUES ET MOINS VALUE DE CESSION | D12: x
A13: NOTE 3E | B13: INFORMATIONS SUR LES REEVALUATIONS EFFECTUEES PAR L’ENTITE | D13: x
A14: NOTE 3F | B14: TABLEAU D’ETALEMENT DES CHARGES IMMOBILISEES | C14: x
A15: NOTE 4 | B15: IMMOBILISATIONS FINANCIERES | D15: x
A16: NOTE 5 | B16: ACTIF CIRCULANT HAO | D16: x
A17: NOTE 6 | B17: STOCKS ET ENCOURS | C17: x
A18: NOTE 7 | B18: CLIENTS | C18: x
A19: NOTE 8 | B19: AUTRES CREANCES | D19: x
A20: NOTE 9 | B20: TITRES DE PLACEMENT | D20: x
A21: NOTE 10 | B21: VALEUR A ENCAISSER | D21: x
A22: NOTE 11 | B22: DISPONIBILITES | D22: x
A23: NOTE 12 | B23: ECARTS DE CONVERSION | D23: x
A24: NOTE 13 | B24: CAPITAL : VALEUR NOMINALE DES ACTIONS OU PARTS | C24: x
A25: NOTE 14 | B25: PRIMES ET RESERVES | C25: x
A26: NOTE 15A | B26: SUBVENTIONS ET PROVISIONS REGLEMENTEES | D26: x
A27: NOTE 15B | B27: AUTRES FONDS PROPRES | D27: x
A28: NOTE 16A | B28: DETTES FINANCIERES ET RESSOURCES ASSIMILEES | D28: x
A29: NOTE 16B | B29: ENGAGEMENTS DE RETRAITE ET AVANTAGES ASSIMILEES (METHODE ACTUARIELLE) | D29: x
A30: NOTE 16B bis | B30: ENGAGEMENTS DE RETRAITE ET AVANTAGES ASSIMILEES (METHODE ACTUARIELLE) | D30: x
A31: NOTE 16C | B31: ACTIFS ET PASSIFS EVENTUELS | C31: x
A32: NOTE 17 | B32: FOURNISSEURS D’EXPLOITATION | D32: x
A33: NOTE 18 | B33: DETTES FISCALES ET SOCIALES | D33: x
A34: NOTE 19 | B34: AUTRES DETTES ET PROVISIONS POUR RISQUES A COURT TERME | C34: x
A35: NOTE 20 | B35: BANQUES, CREDITS D’ESCOMPTE ET DE TRESORERIE | C35: x
A36: NOTE 21 | B36: CHIFFRE D’AFFAIRES ET AUTRES PRODUITS | C36: x
A37: NOTE 22 | B37: ACHATS | C37: x
A38: NOTE 23 | B38: TRANSPORTS | D38: x
A39: NOTE 24 | B39: SERVICES EXTERIEURS | C39: x
A40: NOTE 25 | B40: IMPOTS ET TAXES | C40: x
A41: NOTE 26 | B41: AUTRES CHARGES | D41: x
A42: NOTE 27A | B42: CHARGES DE PERSONNEL | C42: x
A43: NOTE 27B | B43: EFFECTIFS, MASSE SALARIALE ET PERSONNEL EXTERIEUR | C43: x
A44: NOTE 28 | B44: PROVISIONS ET DEPRECIATIONS INSCRITES AU BILAN | C44: x
A45: NOTE 29 | B45: CHARGES ET REVENUS FINANCIERES | D45: x
A46: NOTE 30 | B46: AUTRES CHARGES ET PRODUITS HAO | C46: x
A47: NOTE 31 | B47: REPARTITION DU RESULTAT ET AUTRES ELEMENTS CARACTERISTIQUES DES CINQ DERNIERES EXERCICES | C47: x
A48: NOTE 32 | B48: PRODUCTION DE L’EXERCICE | D48: x
A49: NOTE 33 | B49: ACHATS DESTINES A LA PRODUCTION | C49: x
A50: NOTE 34 | B50: FICHE DE SYNTHESE DES PRINCIPAUX INDICATEURS FINANCIERS | C50: x
A51: NOTE 35 | B51: LISTE DES INFORMATIONS SOCIALES, ENVIRONNEMENTALES ET SOCIETALES A FOURNIR | C51: x
A52: NOTE 36 | B52: TABLES DES CODES | C52: x
A53: A : Applicable N/A : Non Applicable.

Sheet ACTIF
A4: =_soNom -> Cecotra | E4: =_ExerClos -> Exercice clos le 31/12/2025
A5: =_soId -> 3201810353457 | E5: =_Duree -> Durée (en mois) 12
A6: BILAN AU 31 DECEMBRE
A7: REF | B7: ACTIF | C7: Note | D7: =_ExerFin -> 31/12/2025 | G7: =_ExerFin1 -> 31/12/2024
D9: BRUT | E9: AMORT ET DEPREC | F9: NET | G9: NET
A10: AD | B10: IMMOBILISATIONS INCORPORELLES | C10: 3 | D10: =SUM(D11:D14) -> 0 | E10: =SUM(E11:E14) -> 0 | F10: =SUM(F11:F14) -> 0 | G10: =SUM(G11:G14) -> 0
A11: AE | B11: Frais de développement et de prospection | D11: 0 | E11: 0 | F11: =D11-E11 -> 0 | G11: 0
A12: AF | B12: Brevets, licences, logiciels, et droits similaires | D12: 0 | E12: 0 | F12: =D12-E12 -> 0 | G12: 0
A13: AG | B13: Fonds commercial et droit au bail | D13: 0 | E13: 0 | F13: =D13-E13 -> 0 | G13: 0
A14: AH | B14: Autres immobilisations incorporelles | D14: 0 | E14: 0 | F14: =D14-E14 -> 0 | G14: 0
A15: AI | B15: IMMOBILISATIONS CORPORELLES | C15: 3 | D15: =SUM(D16:D23) -> 4191653 | E15: =SUM(E16:E23) -> 1387058 | F15: =SUM(F16:F23) -> 2804595 | G15: =SUM(G16:G23) -> 2804595
A16: AJ | B16: Terrains (1) | D16: 0 | E16: 0 | F16: =D16-E16 -> 0 | G16: 0
B17: (1) dont Placement en Net………../…………
A18: AK | B18: Bâtiments | D18: 0 | E18: 0 | F18: =D18-E18 -> 0 | G18: 0
B19: (1) dont Placement en Net…........./…...…........
A20: AL | B20: Aménagements, agencements et installations | D20: 482083 | E20: 96416 | F20: =D20-E20 -> 385667 | G20: 385667
A21: AM | B21: Matériel, mobilier et actifs biologiques | D21: 965930 | E21: 193186 | F21: =D21-E21 -> 772744 | G21: 772744
A22: AN | B22: Matériel de transport | D22: 2743640 | E22: 1097456 | F22: =D22-E22 -> 1646184 | G22: 1646184
A23: AP | B23: Avances et acomptes versés sur immobilisations | C23: 3 | D23: 0 | E23: 0 | F23: =D23-E23 -> 0 | G23: 0
A24: AQ | B24: IMMOBILISATIONS FINANCIERES | C24: 4 | D24: =SUM(D25:D26) -> 562500 | E24: =SUM(E25:E26) -> 0 | F24: =SUM(F25:F26) -> 562500 | G24: =SUM(G25:G26) -> 562500
A25: AR | B25: Titres de participation | D25: 0 | E25: 0 | F25: =D25-E25 -> 0 | G25: 0
A26: AS | B26: Autres immobilisations financières | D26: 562500 | E26: 0 | F26: =D26-E26 -> 562500 | G26: 562500
A27: AZ | B27: TOTAL ACTIF IMMOBILISE | D27: =SUM(D10+D15+D24) -> 4754153 | E27: =SUM(E10+E15+E24) -> 1387058 | F27: =SUM(F10+F15+F24) -> 3367095 | G27: =SUM(G10+G15+G24) -> 3367095
A28: BA | B28: ACTIF CIRCULANT HAO | C28: 5 | D28: 0 | E28: 0 | F28: =D28-E28 -> 0 | G28: 0
A29: BB | B29: STOCKS ET ENCOURS | C29: 6 | D29: 52704386 | E29: 0 | F29: =D29-E29 -> 52704386 | G29: 52704386
A30: BG | B30: CREANCES ET EMPLOIS ASSIMILES | D30: =SUM(D31:D33) -> 22783128 | E30: =SUM(E31:E33) -> 0 | F30: =SUM(F31:F33) -> 22783128 | G30: =SUM(G31:G33) -> 72100
A31: BH | B31: Fournisseurs avances versées | C31: 17 | D31: 0 | E31: 0 | F31: =D31-E31 -> 0 | G31: 0
A32: BI | B32: Clients | C32: 7 | D32: 22783128 | E32: 0 | F32: =D32-E32 -> 22783128 | G32: 72100
A33: BJ | B33: Autres créances | C33: 8 | D33: 0 | E33: 0 | F33: =D33-E33 -> 0 | G33: 0
A34: BK | B34: TOTAL ACTIF CIRCULANT | D34: =+D28+D29+D30 -> 75487514 | E34: =+E28+E29+E30 -> 0 | F34: =+D34-E34 -> 75487514 | G34: =G28+G29+G30 -> 52776486
A35: BQ | B35: Titres de placement | C35: 9 | D35: 0 | E35: 0 | F35: =D35-E35 -> 0 | G35: 0
A36: BR | B36: Valeurs à encaisser | C36: 10 | D36: 0 | E36: 0 | F36: =D36-E36 -> 0 | G36: 0
A37: BS | B37: Banques, chèques postaux, caisse et assimilés | C37: 11 | D37: 125136 | E37: 0 | F37: =D37-E37 -> 125136 | G37: 0
A38: BT | B38: TOTAL TRESORERIE-ACTIF | D38: =SUM(D35:D37) -> 125136 | E38: =SUM(E35:E37) -> 0 | F38: =SUM(F35:F37) -> 125136 | G38: =SUM(G35:G37) -> 0
A39: BU | B39: Ecart de conversion-Actif | C39: 12 | D39: 0 | E39: 0 | F39: =D39-E39 -> 0 | G39: 0
A40: BZ | B40: TOTAL GENERAL | D40: =SUM(D27+D34+D38+D39) -> 80366803 | E40: =SUM(E27+E34+E38+E39) -> 1387058 | F40: =SUM(F27+F34+F38+F39) -> 78979745 | G40: =SUM(G27+G34+G38+G39) -> 56143581

Sheet PASSIF
A6: =_soNom -> Cecotra | D6: =_ExerClos -> Exercice clos le 31/12/2025
A7: =_soId -> 3201810353457 | D7: =_Duree -> Durée (en mois) 12
A8: BILAN AU 31 DECEMBRE
A9: REF | B9: PASSIF | C9: Note | D9: =_ExerFin -> 31/12/2025 | E9: =_ExerFin1 -> 31/12/2024
D11: NET | E11: NET
A12: CA | B12: Capital | C12: 13 | D12: 1000000 | E12: 1000000
A13: CB | B13: Apporteurs capital non appelé (-) | C13: 13 | D13: 0 | E13: 0
A14: CD | B14: Primes liées au capital social | C14: 14 | D14: 0 | E14: 0
A15: CE | B15: Ecarts de réévaluation | C15: 3e | D15: 0 | E15: 0
A16: CF | B16: Réserves indisponibles | C16: 14 | D16: 0 | E16: 0
A17: CG | B17: Réserves libres | C17: 14 | D17: 0 | E17: 0
A18: CH | B18: Report à nouveau (+ ou -) | C18: 14 | D18: 29907501 | E18: 29907501
A19: CJ | B19: Résultat net de l'exercice (bénéfice + ou perte -) | D19: 16428637 | E19: 418023
A20: CL | B20: Subventions d'investissement | C20: 15 | D20: 0 | E20: 0
A21: CM | B21: Provisions réglementées | C21: 15 | D21: 0 | E21: 0
A22: CP | B22: TOTAL CAPITAUX PROPRES ET RESSOURCES ASSIMILEES | D22: =SUM(D12:D21) -> 47336138 | E22: =SUM(E12:E21) -> 31325524
A23: DA | B23: Emprunts et dettes financières diverses | C23: 16 | D23: 0 | E23: 0
A24: DB | B24: Dettes de location acquisition | C24: 16 | D24: 0 | E24: 0
A25: DC | B25: Provisions pour risques et charges | C25: 16 | D25: 0 | E25: 0
A26: DD | B26: TOTAL DETTES FINANCIERES ET RESSOURCES ASSIMILEES | D26: =SUM(D23:D25) -> 0 | E26: =SUM(E23:E25) -> 0
A27: DF | B27: TOTAL RESSOURCES STABLES | D27: =D22+D26 -> 47336138 | E27: =E22+E26 -> 31325524
A28: DH | B28: Dettes circulantes HAO | C28: 5 | D28: 0 | E28: 0
A29: DI | B29: Clients, avances reçues | C29: 7 | D29: 0 | E29: 0
A30: DJ | B30: Fournisseurs d'exploitation | C30: 17 | D30: 22165344 | E30: 22165344
A31: DK | B31: Dettes fiscales et sociales | C31: 18 | D31: 7962190 | E31: 1100590
A32: DM | B32: Autres dettes | C32: 19 | D32: 1516073 | E32: 1516073
A33: DN | B33: Provisions pour risques à court terme | C33: 19 | D33: 0 | E33: 0
A34: DP | B34: TOTAL PASSIF CIRCULANT | D34: =SUM(D28:D33) -> 31643607 | E34: =SUM(E28:E33) -> 24782007
A35: DQ | B35: Banques, crédits d'escompte | C35: 20 | D35: 0 | E35: 0
A36: DR | B36: Banques, établissements financiers et crédits de trésorerie | C36: 20 | D36: 0 | E36: 36050
A37: DT | B37: TOTAL TRESORERIE-PASSIF | D37: =+D35+D36 -> 0 | E37: =E35+E36 -> 36050
A38: DV | B38: Ecart de conversion-Passif | C38: 12 | D38: 0 | E38: 0
A39: DZ | B39: TOTAL GENERAL | D39: =SUM(D27+D34+D37+D38) -> 78979745 | E39: =SUM(E27+E34+E37+E38) -> 56143581

Sheet RESULTAT
A3: =_soNom -> Cecotra | D3: =_ExerClos -> Exercice clos le 31/12/2025
A4: =_soId -> 3201810353457 | D4: =_Duree -> Durée (en mois) 12
A5: COMPTE DE RESULTAT
A6: REF | B6: LIBELLES | D6: NOTE | E6: =_ExerFin -> 31/12/2025 | F6: =_ExerFin1 -> 31/12/2024
E8: NET | F8: NET
A9: TA | B9: Ventes de marchandises A | C9: + | D9: 21 | E9: 983417641 | F9: 105559492
A10: RA | B10: Achats de marchandises | C10: - | D10: 22 | E10: 955960941 | F10: 98853250
A11: RB | B11: Variation de stocks de marchandises | C11: -/+ | D11: 6 | E11: 0 | F11: 0
A12: XA | B12: MARGE COMMERCIALE (Somme TA à RB) | E12: =E9-E10-E11 -> 27456700 | F12: =F9-F10-F11 -> 6706242
A13: TB | B13: Ventes de produits fabriqués B | C13: + | D13: 21 | E13: 0 | F13: 0
A14: TC | B14: Travaux, services vendus C | C14: + | D14: 21 | E14: 0 | F14: 0
A15: TD | B15: Produits accessoires D | C15: + | D15: 21 | E15: 0 | F15: 0
A16: XB | B16: CHIFFRE D'AFFAIRES (A + B + C + D) | E16: =E9+E13+E14+E15 -> 983417641 | F16: =F9+F13+F14+F15 -> 105559492
A17: TE | B17: Production stockée (ou déstockage) | C17: -/+ | D17: 6 | E17: 0 | F17: 0
A18: TF | B18: Production immobilisée | D18: 21 | E18: 0 | F18: 0
A19: TG | B19: Subventions d’exploitation | D19: 21 | E19: 0 | F19: 0
A20: TH | B20: Autres produits | C20: + | D20: 21 | E20: 0 | F20: 0
A21: TI | B21: Transferts de charges d'exploitation | C21: + | D21: 12 | E21: 0 | F21: 0
A22: RC | B22: Achats de matières premières et fournitures liées | C22: - | D22: 22 | E22: 0 | F22: 0
A23: RD | B23: Variation de stocks de matières premières et fournitures liées | C23: -/+ | D23: 6 | E23: 0 | F23: 0
A24: RE | B24: Autres achats | C24: - | D24: 22 | E24: 0 | F24: 0
A25: RF | B25: Variation de stocks d’autres approvisionnements | C25: -/+ | D25: 6 | E25: 0 | F25: 0
A26: RG | B26: Transports | C26: - | D26: 23 | E26: 0 | F26: 0
A27: RH | B27: Services extérieurs | C27: - | D27: 24 | E27: 746886 | F27: 639000
A28: RI | B28: Impôts et taxes | C28: - | D28: 25 | E28: 124800 | F28: 124800
A29: RJ | B29: Autres charges | C29: - | D29: 26 | E29: 0 | F29: 62500
A30: XC | B30: VALEUR AJOUTEE (XB +RA+RB) + (somme TE à RJ) | E30: =E16-E10-E11+E17+E18+E19+E20+E21-E22-E23-E24-E25-E26-E27-E28-E29 -> 26585014 | F30: =F16-F10-F11+F17+F18+F19+F20+F21-F22-F23-F24-F25-F26-F27-F28-F29 -> 5879942
A31: RK | B31: Charges de personnel | C31: - | D31: 27 | E31: 3712800 | F31: 3712800
A32: XD | B32: EXCEDENT BRUT D'EXPLOITATION (XC+RK) | D32: 28 | E32: =E30-E31 -> 22872214 | F32: =F30-F31 -> 2167142
A33: TJ | B33: Reprises d’amortissements, provisions et dépréciations | C33: + | D33: 28 | E33: 0 | F33: 0
A34: RL | B34: Dotations aux amortissements, aux provisions et dépréciations | C34: - | D34: 3C&28 | E34: 0 | F34: 693529
A35: XE | B35: RESULTAT D'EXPLOITATION (XD+TJ+ RL) | E35: =E32+E33-E34 -> 22872214 | F35: =F32+F33-F34 -> 1473613
A36: TK | B36: Revenus financiers et assimilés | C36: + | D36: 29 | E36: 0 | F36: 0
A37: TL | B37: Reprises de provisions et dépréciations financières | C37: + | D37: 28 | E37: 0 | F37: 0
A38: TM | B38: Transferts de charges financières | C38: + | D38: 12 | E38: 0 | F38: 0
A39: RM | B39: Frais financiers et charges assimilées | C39: - | D39: 29 | E39: 0 | F39: 0
A40: RN | B40: Dotations aux provisions et aux dépréciations financières | C40: - | D40: 3C&28 | E40: 0 | F40: 0
A41: XF | B41: RESULTAT FINANCIER (somme TK à RN) | E41: =E36+E37+E38-E39-E40 -> 0 | F41: =F36+F37+F38-F39-F40 -> 0
A42: XG | B42: RESULTAT DES ACTIVITES ORDINAIRES (XE+XF) | E42: =E35+E41 -> 22872214 | F42: =F35+F41 -> 1473613
A43: TN | B43: Produits des cessions d'immobilisations | C43: + | D43: 3D | E43: 0 | F43: 0
A44: TO | B44: Autres Produits HAO | C44: + | D44: 30 | E44: 0 | F44: 0
A45: RO | B45: Valeurs comptables des cessions d'immobilisations | C45: - | D45: 3D | E45: 0 | F45: 0
A46: RP | B46: Autres Charges HAO | C46: - | D46: 30 | E46: 0 | F46: 0
A47: XH | B47: RESULTAT HORS ACTIVITES ORDINAIRES (somme TN à RP) | E47: =E43+E44-E45-E46 -> 0 | F47: =F43+F44-F45-F46 -> 0
A48: RQ | B48: Participation des travailleurs | C48: - | D48: 30 | E48: 0 | F48: 0
A49: RS | B49: Impôts sur le résultat | C49: - | E49: 6861600 | F49: 1055590
A50: XI | B50: RESULTAT NET (XG+XH+RQ+RS) | E50: =E42+E47-E48-E49 -> 16010614 | F50: =F42+F47-F48-F49 -> 418023

Sheet TFT
B5: =_soNom -> Cecotra | G5: =_ExerClos -> Exercice clos le 31/12/2025
B6: =_soId -> 3201810353457 | G6: =_Duree -> Durée (en mois) 12
B8: TABLEAU DES FLUX DE TRESORERIE
B9: REF | C9: LIBELLES | G9: Note | H9: =_ExerFin -> 31/12/2025 | I9: =_ExerFin1 -> 31/12/2024
B11: ZA | C11: Trésorerie nette au 1er janvier | F11: A | H11: -36050 | I11: 144039
C12: (Trésorerie actif N-1 - Trésorerie passif N-1)
C13: Flux de trésorerie provenant des activités opérationnelles
B14: FA | C14: Capacité d'Autofinancement Globale (CAFG) | H14: 16010614 | I14: 1531924
B15: FB | C15: - Variation Actif circulant HAO (1) | H15: 0 | I15: 0
B16: FC | C16: - Variation des stocks | H16: 0 | I16: 0
B17: FD | C17: - Variation des créances | H17: 22711028 | I17: 0
B18: FE | C18: + Variation du passif circulant (1) | H18: 6861600 | I18: -1675963
C19: Variation du BF lié aux activités opérationnelles (FB+FC+FD-FE) : | D19: =SUM(H15:H18) -> 29572628 | E19: =SUM(I15:I18) -> -1675963 | H19: =H15+H16+H17-H18 -> 15849428 | I19: =I15+I16+I17-I18 -> 1675963
B20: ZB | C20: Flux de trésorerie provenant des activités opérationnelles (somme FA à FE) | F20: B | H20: =H14-H15-H16-H17+H18 -> 161186 | I20: =I14-I15-I16-I17+I18 -> -144039
C21: Flux de trésorerie provenant des activités d’investissements
B22: FF | C22: - Décaissements liés aux acquisitions d'immobilisations incorporelles | H22: 0
B23: FG | C23: - Décaissements liés aux acquisitions d'immobilisations corporelles | H23: 0
B24: FH | C24: - Décaissements liés aux acquisitions d'immobilisations financières | H24: 0
B25: FI | C25: + Encaissements liés aux cessions d’immobilisations incorporelles et corporelles | H25: 0 | I25: 0
B26: FJ | C26: + Encaissements liés aux cessions d’immobilisations financières | H26: 0 | I26: 0
B27: ZC | C27: Flux de trésorerie provenant des activités d’investissement (somme FF à FJ) | F27: C | H27: =-H22-H23-H24+H25+H26 -> 0
C28: Flux de trésorerie provenant du financement par les capitaux propres
B29: FK | C29: + Augmentations de capital par apports nouveaux | H29: 0
B30: FL | C30: + Subventions d'investissement reçues | H30: 0
B31: FM | C31: - Prélèvements sur le capital | H31: 0
B32: FN | C32: - Dividendes versés | H32: 0
B33: ZD | C33: Flux de trésorerie provenant des capitaux propres (somme FK à FN) | F33: D | H33: =H29+H30-H31-H32 -> 0 | I33: =I29+I30-I31-I32 -> 0
C34: Trésorerie provenant du financement par les capitaux étrangers
B35: FO | C35: + Emprunts | H35: 0
B36: FP | C36: + Autres dettes financières | H36: 0
B37: FQ | C37: - Remboursements des emprunts et autres dettes financières | H37: 0
B38: ZE | C38: Flux de trésorerie provenant des capitaux étrangers (somme FO à FQ) | F38: E | H38: =H35+H36-H37 -> 0 | I38: =I35+I36-I37 -> 0
B39: ZF | C39: Flux de trésorerie provenant des activités de financement (D+E) | F39: F | H39: =H33+H38 -> 0
B40: ZG | C40: VARIATION DE LA TRÉSORERIE NETTE DE LA PÉRIODE (B+C+F) | F40: G | H40: =H20+H27+H39 -> 161186 | I40: -144039
B41: ZH | C41: Trésorerie nette au 31 Décembre (G+A) | F41: H | H41: =H11+H40 -> 125136
C42: Contrôle: Trésorerie actif N - Trésorerie passif N = 125 136
B43: [1] à l’exclusion des variations des créances et dettes liées aux activités d’investissement (variation des créances sur cession d’immobilisation et des dettes sur acquisition ou production d’immobilisation) et de financement (par exemple variation des créances sur subventions d’investissements reçues).

Sheet NOTE 1
A5: =_soNom -> Cecotra | D5: =_ExerClos -> Exercice clos le 31/12/2025
A6: =_soId -> 3201810353457 | D6: =_Duree -> Durée (en mois) 12
A8: DETTES GARANTIES PAR DES SURETES REELLES
A9: LIBELLES | B9: Note | C9: Montant brut | D9: SURETES REELLES
D10: Hypothèques | E10: Nantissements | F10: Gages/
F11: autres
A12: Dettes financières et ressources assimilées :
A13: Emprunts obligataires convertibles
A14: Autres emprunts obligataires
A15: Emprunts et dettes des établissements de crédit
A16: Autres dettes financières
A17: SOUS TOTAL (1) | C17: =SUM(C13:C16) -> 0 | D17: =SUM(D13:D16) -> 0 | E17: =SUM(E13:E16) -> 0 | F17: =SUM(F13:F16) -> 0
A19: Dettes de location-acquisition :
A20: Dettes de crédit-bail immobilier
A21: Dettes de crédit-bail mobilier
A22: Dettes sur contrats de location-vente
A23: Dettes sur contrats de location-acquisition
A24: SOUS TOTAL (2) | C24: =SUM(C20:C23) -> 0 | D24: =SUM(D20:D23) -> 0 | E24: =SUM(E20:E23) -> 0 | F24: =SUM(F20:F23) -> 0
A26: Dettes du passif circulant :
A27: Fournisseurs et comptes rattachés
A28: Clients
A29: Personnel
A30: Sécurité sociale et organismes sociaux
A31: Etat
A32: Organismes internationaux
A33: Associés et groupe
A34: Créditeurs divers
A35: SOUS TOTAL (3) | C35: =SUM(C27:C34) -> 0 | D35: =SUM(D27:D34) -> 0 | E35: =SUM(E27:E34) -> 0 | F35: =SUM(F27:F34) -> 0
A36: TOTAL (1) + (2) + (3) | C36: =+C17+C24+C35 -> 0 | D36: =+D17+D24+D35 -> 0 | E36: =+E17+E24+E35 -> 0 | F36: =+F17+F24+F35 -> 0
A37: ENGAGEMENTS FINANCIERS | E37: Engagements donnés | F37: Engagements reçus
A38: Engagements consentis à des entités liées
A39: Primes de remboursement non échues
A40: Avals, cautions, garanties
A41: hypothèques, nantissements, gages, autres
A42: Effets escomptés non échus
A43: Créances commerciales et professionnelles cédées
A44: Abandons de créances conditionnels
A45: TOTAL | E45: =SUM(E38:E44) -> 0 | F45: =SUM(F38:F44) -> 0
A46: Commentaire :
A47: • Indiquer la raison d'être des suretés.

Sheet NOTE 2
B5: =_soNom -> Cecotra | E5: =_ExerClos -> Exercice clos le 31/12/2025
B6: =_soId -> 3201810353457 | E6: =_Duree -> Durée (en mois) 12
B8: NOTE 2
B9: INFORMATIONS OBLIGATOIRES
B10: A - DECLARATION DE CONFORMITE AU SYSCOHADA
B13: B - REGLES ET METHODES COMPTABLES
B16: C- DEROGATION AUX POSTULATS ET CONVENTIONS COMPTABLES
B18: D - INFORMATIONS COMPLEMENTAIRES RELATIVES AU BILAN, AU COMPTE DE
B19: RESULTAT ET AU TABLEAU DES FLUX DE TRESORERIE

Sheet NOTE 3A
A5: =_soNom -> Cecotra | E5: =_ExerClos -> Exercice clos le 31/12/2025
A6: =_soId -> 3201810353457 | E6: =_Duree -> Durée (en mois) 12
B8: NOTE 3A
A9: IMMOBILISATION BRUTE
A11: SITUATIONS ET MOUVEMENTS | B11: MONTANT | C11: Acquisitions | D11: Virements | E11: Suite à une | F11: Cessions | G11: Virements | H11: MONTANT
B12: BRUT A | C12: Apports | D12: de | E12: réévaluation | F12: Scissions | G12: de | H12: BRUT A LA
A13: RUBRIQUES | B13: L'OUVERTURE DE | C13: Créations | D13: poste à poste | E13: Pratiquée au cours | F13: Hors service | G13: poste à | H13: CLOTURE DE
B14: L’EXERCICE | E14: de l’exercice | G14: poste | H14: L’EXERCICE
A15: IMMOBILISATIONS INCORPORELLES | B15: =SUM(B16:B19) -> 0 | C15: =SUM(C16:C19) -> 0 | D15: =SUM(D16:D19) -> 0 | E15: =SUM(E16:E19) -> 0 | F15: =SUM(F16:F19) -> 0 | G15: =SUM(G16:G19) -> 0 | H15: =SUM(H16:H19) -> 0
A16: Frais de développement et de prospection
A17: Brevets, licences, logiciels, et droits similaires
A18: Fonds commercial et droit au bail
A19: Autres immobilisations incorporelles
A20: IMMOBILISATIONS CORPORELLES | B20: =SUM(B21:B27) -> 4191653 | C20: =SUM(C21:C27) -> 0 | D20: =SUM(D21:D27) -> 0 | E20: =SUM(E21:E27) -> 0 | F20: =SUM(F22:F27) -> 0 | G20: =SUM(G21:G27) -> 0 | H20: =SUM(H21:H27) -> 4191653
A21: Terrains hors immeuble de placement
A22: Terrains - immeuble de placement | H22: =B22+C22+D22+E22-F22-G22 -> 0
A23: Bâtiments hors immeuble de placement
A24: Bâtiments - immeuble de placement | H24: =B24+C24+D24+E24-F24-G24 -> 0
A25: Aménagements, agencements et installations | B25: 482083 | H25: 482083
A26: Matériel, mobilier et actifs biologiques | B26: 965930 | H26: 965930
A27: Matériel de transport | B27: 2743640 | H27: 2743640
A28: AVANCES ET ACOMPTES VERSES SUR IMMOBILISATIONS | B28: =SUM(B29:B30) -> 0 | C28: =SUM(C29:C30) -> 0 | D28: =SUM(D29:D30) -> 0 | E28: =SUM(E29:E30) -> 0 | F28: =SUM(F29:F30) -> 0 | G28: =SUM(G29:G30) -> 0 | H28: =SUM(H29:H30) -> 0
A29: Immobilisations incorporelles
A30: Immobilisations corporelles
A31: IMMOBILISATIONS FINANCIERES | B31: =SUM(B32:B33) -> 562500 | C31: =SUM(C32:C33) -> 0 | D31: =SUM(D32:D33) -> 0 | E31: =SUM(E32:E33) -> 0 | F31: =SUM(F32:F33) -> 0 | G31: =SUM(G32:G33) -> 0 | H31: =SUM(H32:H33) -> 562500
A32: Titres de participation
A33: Autres immobilisations financières | B33: 562500 | H33: 562500
A34: TOTAL GENERAL | B34: =B15+B20+B28+B31 -> 4754153 | C34: =C15+C20+C28+C31 -> 0 | D34: =D15+D20+D28+D31 -> 0 | E34: =E15+E20+E28+E31 -> 0 | F34: =F15+F20+F28+F31 -> 0 | G34: =G15+G20+G28+G31 -> 0 | H34: =H15+H20+H28+H31 -> 4754153
A36: Commentaire :

Sheet NOTE 3B
A5: =_soNom -> Cecotra | E5: =_ExerClos -> Exercice clos le 31/12/2025
A6: =_soId -> 3201810353457 | E6: =_Duree -> Durée (en mois) 12
A8: NOTE 3B
A9: BIENS PRIS EN LOCATION ACQUISITION
A10: SITUATIONS ET MOUVEMENTS | B10: NATURE | C10: A | D10: AUGMENTATIONS B | G10: DIMINUTIONS C | I10: D = A + B - C
B11: DU CONTRAT
B12: (I ; M ; A)
B13: [1]
C15: MONTANT | D15: Acquisitions | E15: Virements de | F15: Suite à une | G15: Cessions | H15: Virements de | I15: MONTANT
C16: BRUT A | D16: Apports | E16: poste à poste | F16: Réévaluation | G16: Scissions | H16: poste à | I16: BRUT A LA
C17: L'OUVERTURE | D17: Créations | F17: Pratiquée | G17: Hors service | H17: poste | I17: CLOTURE DE
A18: RUBRIQUES | C18: DE L'EXERCICE | F18: au cours | I18: L'EXERCICE
C19: L'EXERCICE | F19: de l'exercice
A20: Brevets, licences, logiciels et droits similaires
A21: Fonds commercial et droit au bail
A22: Autres immobilisations incorporelles
A23: SOUS TOTAL : IMMOBILISATIONS INCORPORELLES | C23: =SUM(C20:C22) -> 0 | D23: =SUM(D20:D22) -> 0 | E23: =SUM(E20:E22) -> 0 | F23: =SUM(F20:F22) -> 0 | G23: =SUM(G20:G22) -> 0 | H23: =SUM(H20:H22) -> 0 | I23: =C23+D23+E23+F23-G23-H23 -> 0
A24: Terrains
A25: Bâtiments
A26: Aménagements, agencements et installations
A27: Matériel, mobilier et actifs biologiques
A28: Matériel de transport
A29: SOUS TOTAL : IMMOBILISATIONS CORPORELLES | C29: =SUM(C24:C28) -> 0 | D29: =SUM(D24:D28) -> 0 | E29: =SUM(E24:E28) -> 0 | F29: =SUM(F24:F28) -> 0 | G29: =SUM(G24:G28) -> 0 | H29: =SUM(H24:H28) -> 0 | I29: =C29+D29+E29+F29-G29-H29 -> 0
A31: TOTAL GENERAL | C31: =+C23+C29 -> 0 | D31: =+D23+D29 -> 0 | E31: =+E23+E29 -> 0 | F31: =+F23+F29 -> 0 | G31: =+G23+G29 -> 0 | H31: =+H23+H29 -> 0 | I31: =+C31+D31+E31+F31-G31-H31 -> 0
A34: [1] I : Crédit-bail immobilier ; M : Crédit-bail mobilier ; A : Autres contrats (dédoubler le poste si montants significatifs)
A36: Commentaire :
A37: Indiquer la nature du bien, le nom du bailleur et la durée du bail.

Sheet NOTE 3C
A5: =_soNom -> Cecotra | D5: =_ExerClos -> Exercice clos le 31/12/2025
A6: =_soId -> 3201810353457 | D6: =_Duree -> Durée (en mois) 12
A8: NOTE 3C
A9: IMMOBILISATION (AMORTISSEMENTS)
A11: SITUATIONS ET MOUVEMENTS | B11: A | C11: B | D11: C | E11: D = A + B - C
A14: RUBRIQUES | B14: AMORTISSEMENTS CUMULES A L’OUVERTURE DE L’EXERCICE | C14: AUGMENTATIONS : DOTATIONS DE l’EXERCICE | D14: DIMINUTIONS : Amortissements relatifs aux éléments sortis de l’actif | E14: CUMUL DES AMORTISSEMENTS A LA CLOTURE DE L’EXERCICE
A15: Frais de développement et de prospection | E15: =B15+C15-D15 -> 0
A16: Brevets, licences, logiciels et droits similaires | E16: =B16+C16-D16 -> 0
A17: Fonds commercial et droit au bail | E17: =B17+C17-D17 -> 0
A18: Autres immobilisations incorporelles | E18: =B18+C18-D18 -> 0
A19: SOUS TOTAL : IMMOBILISATIONS INCORPORELLES | B19: =SUM(B15:B18) -> 0 | C19: =SUM(C15:C18) -> 0 | D19: =SUM(D15:D18) -> 0 | E19: =SUM(E15:E18) -> 0
A20: Terrains hors immeuble de placement | E20: =B20+C20-D20 -> 0
A21: Terrains-immeuble de placement | E21: =B21+C21-D21 -> 0
A22: Bâtiments hors immeuble de placement | E22: =B22+C22-D22 -> 0
A23: Bâtiments-immeuble de placement | E23: =B23+C23-D23 -> 0
A24: Aménagements, agencements et installations | B24: 96416 | E24: =B24+C24-D24 -> 96416
A25: Matériel, mobilier et actifs biologiques | B25: 193186 | E25: =B25+C25-D25 -> 193186
A26: Matériel de transport | B26: 1097456 | E26: =B26+C26-D26 -> 1097456
A27: SOUS TOTAL : IMMOBILISATIONS CORPORELLES | B27: =SUM(B20:B26) -> 1387058 | C27: =SUM(C20:C26) -> 0 | D27: =SUM(D20:D26) -> 0 | E27: =SUM(E20:E26) -> 1387058
A29: TOTAL GENERAL | B29: =B27+B19 -> 1387058 | C29: =C27+C19 -> 0 | D29: =D27+D19 -> 0 | E29: =E27+E19 -> 1387058
A31: Commentaire :

Sheet NOTE 3D
B1: NOTE 3D : IMMOBILISATIONS (PLUS-VALUES ET MOINS VALUE DE CESSION)
B6: =_soNom -> Cecotra | E6: =_ExerClos -> Exercice clos le 31/12/2025
B7: =_soId -> 3201810353457 | E7: =_Duree -> Durée (en mois) 12
B9: NOTE 3D
B10: IMMOBILISATIONS : PLUS-VALUES ET MOINS VALUE DE CESSION
C11: MONTANT | D11: AMORTISSEMENTS | E11: VALEUR | F11: PRIX | G11: PLUS-VALUE
C12: BRUT | D12: PRATIQUES | E12: COMPTABLE | F12: DE | G12: OU MOINS-VALUE
E13: NETTE | F13: CESSION
C14: A | D14: B | E14: C = A - B | F14: D | G14: E = D - C
B15: Frais de développement et de prospection
B16: Brevets, licences, logiciels et droits similaires
B17: Fonds commercial et droit au bail
B18: Autres immobilisations incorporelles
B19: SOUS TOTAL : IMMOBILISATIONS INCORPORELLES | C19: =SUM(C15:C18) -> 0 | D19: =SUM(D15:D18) -> 0 | E19: =C19-D19 -> 0 | F19: =SUM(F15:F18) -> 0 | G19: =F19-E19 -> 0
B20: Terrains
B21: Bâtiments
B22: Aménagements, agencements et installations
B23: Matériel, mobilier et actifs biologiques
B24: Matériel de transport
B25: SOUS TOTAL : IMMOBILISATIONS CORPORELLES | C25: =SUM(C20:C24) -> 0 | D25: =SUM(D20:D24) -> 0 | E25: =C25-D25 -> 0 | F25: =SUM(F20:F24) -> 0 | G25: =F25-E25 -> 0
B26: Titres de participations
B27: Autres immobilisations financières
B28: SOUS TOTAL : IMMOBILISATIONS FINANCIERES | C28: =SUM(C26:C27) -> 0 | D28: =SUM(D26:D27) -> 0 | E28: =C28-D28 -> 0 | F28: =SUM(F26:F27) -> 0 | G28: =F28-E28 -> 0
B30: TOTAL GENERAL | C30: =C19+C25+C28 -> 0 | D30: =D19+D25+D28 -> 0 | E30: =E19+E25+E28 -> 0 | F30: =F19+F25+F28 -> 0 | G30: =G19+G25+G28 -> 0
B32: Commentaire :
B33: . Mentionner la justification de la cession ainsi que la date et la date de sortie.

Sheet NOTE 3E
A2: NOTE 3D : IMMOBILISATIONS (PLUS-VALUES ET MOINS VALUE DE CESSION)
A7: =_soNom -> Cecotra | B7: =_ExerClos -> Exercice clos le 31/12/2025
A8: =_soId -> 3201810353457 | B8: =_Duree -> Durée (en mois) 12
A9: NOTE 3E : INFORMATIONS SUR LES REEVALUATIONS EFFECTUEES
A10: NOTE 3E
A11: INFORMATIONS SUR LES REEVALUATIONS EFFECTUEES PAR L'ENTITE
A12: Nature et date des réévaluations :
A16: Eléments réévalués par postes du bilan | B16: Montants coûts historiques | C16: Amortissements supplémentaires
A25: Méthode de réévaluation utilisée :
A31: Traitement fiscal de l'écart de réévaluation et des amortissements supplémentaires :
A37: Montant de l'écart incorporé au capital :

Sheet NOTE 4
A6: =_soNom -> Cecotra | E6: =_ExerClos -> Exercice clos le 31/12/2025
A7: =_soId -> 3201810353457 | E7: =_Duree -> Durée (en mois) 12
A9: NOTE 4
A10: IMMOBILISATIONS FINANCIERES
A11: Libellés | B11: =_ExerFin -> 31/12/2025 | C11: =_ExerFin1 -> 31/12/2024 | D11: Variation en % | E11: Créances à un an au plus | F11: Créances à plus d'un an et à | G11: Créances à plus de deux ans
F12: deux ans au plus
A13: Titres de participation | B13: 0 | C13: 0 | D13: =IF(C13=0,0,(B13-C13)/C13)*100 -> 0 | E13: 0
A14: Prêts et créances | B14: 0 | C14: 0 | D14: =IF(C14=0,0,(B14-C14)/C14)*100 -> 0 | E14: 0 | F14: 0 | G14: =B14 - E14 - F14 -> 0
A15: Prêt au personnel | B15: 0 | C15: 0 | D15: =IF(C15=0,0,(B15-C15)/C15)*100 -> 0 | E15: 0 | F15: 0 | G15: =B15 - E15 - F15 -> 0
A16: Créances sur l'état | B16: 0 | C16: 0 | D16: =IF(C16=0,0,(B16-C16)/C16)*100 -> 0 | E16: 0 | F16: 0 | G16: =B16 - E16 - F16 -> 0
A17: Titres immobilisés | B17: 562500 | C17: 0 | D17: =IF(C17=0,0,(B17-C17)/C17)*100 -> 0 | E17: 0 | F17: 0
A18: Dépôts et cautionnements | B18: 0 | C18: 0 | D18: =IF(C18=0,0,(B18-C18)/C18)*100 -> 0 | E18: 0 | F18: 0 | G18: =B18 - E18 - F18 -> 0
A19: Intérêts courus | B19: 0 | C19: 0 | D19: =IF(C19=0,0,(B19-C19)/C19)*100 -> 0
A20: TOTAL BRUT | B20: =SUM(B13:B19) -> 562500 | C20: =SUM(C13:C19) -> 0 | D20: =IF(C20=0,0,(B20-C20)/C20)*100 -> 0 | E20: =SUM(E13:E19) -> 0 | F20: =SUM(F13:F19) -> 0 | G20: =SUM(G13:G19) -> 0
A21: Dépréciations titres de participation | B21: 0 | C21: 0 | D21: =IF(C21=0,0,(B21-C21)/C21)*100 -> 0 | F21: 0 | G21: 0
A22: Dépréciations autres immobilisations | B22: 0 | C22: 0 | D22: =IF(C22=0,0,(B22-C22)/C22)*100 -> 0 | F22: 0 | G22: 0
A23: TOTAL NET DE DEPRECIATION | B23: =B21+B22 -> 0 | C23: =C21+C22 -> 0 | D23: =IF(C23=0,0,(B23-C23)/C23)*100 -> 0 | E23: =+E21+E22 -> 0 | F23: =F21+F22 -> 0 | G23: =G21+G22 -> 0
A24: Liste des filiales et participations :
A25: Dénomination sociale | B25: Localisation (ville / pays) | D25: Valeur d'acquisition | E25: % Détenu | F25: Montant des | G25: Résultat dernier
F26: capitaux propres filiale | G26: exercice filiale
A33: Commentaire :
A34: • Justifier toute variation significative.
A35: • Commenter toutes les créances anciennes.
A36: • Pour les créances relatives à la concession, faire un descriptif de l'accord.
A37: • Indiquer :
A38: - la nature de la créance ;
A39: - la durée de la concession ;
A40: - l'échéance.
A41: • Indiquer le nombre et la date d'acquisition des actions ou parts propres.
A42: • Dépréciation : indiquer les évènements et les circonstances qui ont motivé la dépréciation ou la reprise.

Sheet NOTE 5
A6: =_soNom -> Cecotra | C6: =_ExerClos -> Exercice clos le 31/12/2025
A7: =_soId -> 3201810353457 | C7: =_Duree -> Durée (en mois) 12
A10: NOTE 5
A11: ACTIF CIRCULANT HAO
A13: Libellés | C13: =_ExerFin -> 31/12/2025 | D13: =_ExerFin1 -> 31/12/2024 | E13: Variation en %
A14: Créances sur cessions d'immobilisations | C14: 0 | D14: 0 | E14: =IF(D14=0,0,(C14-D14)/D14)*100 -> 0
A15: Autres créances hors activités ordinaires | C15: 0 | D15: 0 | E15: =IF(D15=0,0,(C15-D15)/D15)*100 -> 0
A16: TOTAL BRUT | C16: =SUM(C14:C15) -> 0 | D16: =SUM(D14:D15) -> 0 | E16: =IF(D16=0,0,(C16-D16)/D16)*100 -> 0
A17: Dépréciations des créances HAO | C17: 0 | D17: 0 | E17: =IF(D17=0,0,(C17-D17)/D17)*100 -> 0
E18: =IF(D18=0,0,(C18-D18)/D18)*100 -> 0
A19: TOTAL NET DE DEPRECIATION | C19: =C17 -> 0 | D19: =D17 -> 0 | E19: =IF(D19=0,0,(C19-D19)/D19)*100 -> 0
A20: Commentaire:
A21: • Commenter toute variation significative.
A22: • Dépréciation : indiquer les évènements et les circonstances qui ont motivé la dépréciation ou la reprise.
A25: DETTES CIRCULANTES HAO
A26: Libellés | C26: =_ExerFin -> 31/12/2025 | D26: =_ExerFin1 -> 31/12/2024 | E26: Variation en %
A27: Fournisseurs d'investissements | C27: 0 | D27: 0 | E27: =IF(D27=0,0,(C27-D27)/D27)*100 -> 0
A28: Fournisseurs d'investissements effets à payer | C28: 0 | D28: 0 | E28: =IF(D28=0,0,(C28-D28)/D28)*100 -> 0
A29: Versements restant à effectuer sur titres de participation et titres immobilisés non libérés | C29: 0 | D29: 0 | E29: =IF(D29=0,0,(C29-D29)/D29)*100 -> 0
A30: Autres dettes hors activités ordinaires | C30: 0 | D30: 0 | E30: =IF(D30=0,0,(C30-D30)/D30)*100 -> 0
A31: TOTAL | C31: =SUM(C27:C30) -> 0 | D31: =SUM(D27:D30) -> 0 | E31: =IF(D31=0,0,(C31-D31)/D31)*100 -> 0
A33: Commentaire :
A35: • Indiquer la date de cession et la nature de l'immobilisation achetée
A36: et/ou cédée.
A37: • Expliciter toute variation significative.

Sheet NOTE 6
A6: =_soNom -> Cecotra | B6: =_ExerClos -> Exercice clos le 31/12/2025
A7: =_soId -> 3201810353457 | B7: =_Duree -> Durée (en mois) 12
A9: NOTE 6
A10: STOCKS ET EN COURS (1)
A11: Libellés | B11: =_ExerFin -> 31/12/2025 | C11: =_ExerFin1 -> 31/12/2024 | D11: Variation en %
A12: Marchandises | B12: 52704386 | C12: 0 | D12: =IF(C12=0,0,(B12-C12)/C12)*100 -> 0
A13: Matières premières et fournitures liées | B13: 0 | C13: 0 | D13: =IF(C13=0,0,(B13-C13)/C13)*100 -> 0
A14: Autres approvisionnements | B14: 0 | C14: 0 | D14: =IF(C14=0,0,(B14-C14)/C14)*100 -> 0
A15: Produits en cours | B15: 0 | C15: 0 | D15: =IF(C15=0,0,(B15-C15)/C15)*100 -> 0
A16: Services en cours | B16: 0 | C16: 0 | D16: =IF(C16=0,0,(B16-C16)/C16)*100 -> 0
A17: Produits finis | B17: 0 | C17: 0 | D17: =IF(C17=0,0,(B17-C17)/C17)*100 -> 0
A18: Produits intermédiaires | B18: 0 | C18: 0 | D18: =IF(C18=0,0,(B18-C18)/C18)*100 -> 0
A19: Stocks en cours de route, en consignation ou en dépôt | D19: =IF(C19=0,0,(B19-C19)/C19)*100 -> 0
A20: TOTAL BRUT STOCKS ET EN COURS | B20: =SUM(B12:B19) -> 52704386 | C20: =SUM(C12:C19) -> 0 | D20: =IF(C20=0,0,(B20-C20)/C20)*100 -> 0
A22: Dépréciations des stocks | B22: 0 | C22: 0 | D22: =IF(C22=0,0,(B22-C22)/C22)*100 -> 0
A24: TOTAL NET DE DEPRECIATION | B24: =+B20-B22 -> 52704386 | C24: =+C20-C22 -> 0 | D24: =IF(C24=0,0,(B24-C24)/C24)*100 -> 0
A25: (1) Les stocks H.A.O. seront inscrits dans l'actif circulant H.A.O. que lorsque leur montant total est significatif (supérieur à 5 % du total de l'actif circulant).
A27: Commentaire :
A28: • Indiquer la date de prise d'inventaire et décrire brièvement la procédure, les méthodes comptables adoptées pour évaluer le stock.
A29: • Commenter toute variation significative des stocks.
A30: • Indiquer le détail des stocks dépréciés et les évènements et circonstances qui ont conduit à la dépréciation et à la reprise.

Sheet NOTE 7
A4: =_soNom -> Cecotra | E4: =_ExerClos -> Exercice clos le 31/12/2025
A5: =_soId -> 3201810353457 | E5: =_Duree -> Durée (en mois) 12
A6: NOTE 7
A7: CLIENTS
A8: Libellés | B8: =_ExerFin -> 31/12/2025 | C8: =_ExerFin1 -> 31/12/2024 | D8: Variation en % | E8: Créances à un an au plus | F8: Créances à plus | G8: Créances à plus de deux ans
F9: d'un an
F10: et à deux
F11: ans au plus
A12: Clients (hors réserves de propriété Groupe) | B12: 22783128 | C12: 0 | D12: =IF(C12=0,0,(B12-C12)/C12)*100 -> 0 | E12: 0 | F12: =+B12 -> 22783128 | G12: 0
A13: Clients effets à recevoir (hors réserves de propriété groupe) | B13: 0 | C13: 0 | D13: =IF(C13=0,0,(B13-C13)/C13)*100 -> 0
A14: Clients et effets à recevoir avec réserves de propriété | B14: 0 | C14: 0 | D14: =IF(C14=0,0,(B14-C14)/C14)*100 -> 0
A15: Clients et effets à recevoir Groupe | B15: 0 | C15: 0 | D15: =IF(C15=0,0,(B15-C15)/C15)*100 -> 0
A16: Créances sur cession d'immobilisations | B16: 0 | C16: 0 | D16: =IF(C16=0,0,(B16-C16)/C16)*100 -> 0
A17: Clients effets escomptés et non échus | B17: 0 | C17: 0 | D17: =IF(C17=0,0,(B17-C17)/C17)*100 -> 0
A18: Créances litigieuses ou douteuses | B18: 0 | C18: 0 | D18: =IF(C18=0,0,(B18-C18)/C18)*100 -> 0
A19: Clients produits à recevoir | B19: 0 | C19: 0 | D19: =IF(C19=0,0,(B19-C19)/C19)*100 -> 0
A20: TOTAL BRUT CLIENTS | B20: =SUM(B12:B19) -> 22783128 | C20: =SUM(C12:C19) -> 0 | D20: =IF(C20=0,0,(B20-C20)/C20)*100 -> 0 | E20: =SUM(E12:E19) -> 0 | F20: =SUM(F12:F19) -> 22783128 | G20: =SUM(G12:G19) -> 0
D21: =IF(C21=0,0,(B21-C21)/C21)*100 -> 0
A22: Dépréciations des comptes clients | B22: 0 | C22: 0 | D22: =IF(C22=0,0,(B22-C22)/C22)*100 -> 0
D23: =IF(C23=0,0,(B23-C23)/C23)*100 -> 0
A24: TOTAL NET DE DEPRECIATION | B24: =+B22 -> 0 | C24: =+C22 -> 0 | D24: =IF(C24=0,0,(B24-C24)/C24)*100 -> 0 | E24: =+E22 -> 0 | F24: =+F22 -> 0 | G24: =+G22 -> 0
A25: Clients, avances reçues hors groupe | B25: 0 | C25: 0 | D25: =IF(C25=0,0,(B25-C25)/C25)*100 -> 0 | F25: 0 | G25: 0
A26: Clients, avances reçues groupe | B26: 0 | C26: 0 | D26: =IF(C26=0,0,(B26-C26)/C26)*100 -> 0 | F26: 0 | G26: 0
A27: Autres clients créditeurs | B27: 0 | C27: 0 | D27: =IF(C27=0,0,(B27-C27)/C27)*100 -> 0 | F27: 0 | G27: 0
A28: TOTAL CLIENTS CREDITEURS | B28: =SUM(B25:B27) -> 0 | C28: =SUM(C25:C27) -> 0 | D28: =IF(C28=0,0,(B28-C28)/C28)*100 -> 0 | E28: =SUM(E25:E27) -> 0 | F28: =SUM(F25:F27) -> 0 | G28: =SUM(G25:G27) -> 0
A29: Commentaire :

Sheet NOTE 8
A5: =_soNom -> Cecotra | E5: =_ExerClos -> Exercice clos le 31/12/2025
E6: =_Duree -> Durée (en mois) 12
A8: NOTE 8
A9: AUTRES CREANCES
A10: Libellés | B10: =_ExerFin -> 31/12/2025 | C10: =_ExerFin1 -> 31/12/2024 | D10: Variation en % | E10: Créances à un an au plus | F10: Créances à plus | G10: Créances à plus de deux ans
F11: d'un an
F12: et à deux
F13: ans au plus
A14: Personnel | B14: 0 | C14: 0 | D14: =IF(C14=0,0,(B14-C14)/C14)*100 -> 0
A15: Organismes sociaux | B15: 0 | C15: 0 | D15: =IF(C15=0,0,(B15-C15)/C15)*100 -> 0
A16: Etat et Collectivités publiques | B16: 0 | C16: 0 | D16: =IF(C16=0,0,(B16-C16)/C16)*100 -> 0 | E16: 0 | F16: =C16 -> 0 | G16: 0
A17: Organismes internationaux | B17: 0 | C17: 0 | D17: =IF(C17=0,0,(B17-C17)/C17)*100 -> 0
A18: Apporteurs, associés et groupe | B18: 0 | C18: 0 | D18: =IF(C18=0,0,(B18-C18)/C18)*100 -> 0
A19: Compte transitoire ajustement spécial lié à la révision du SYSCOHADA | B19: 0 | C19: 0 | D19: =IF(C19=0,0,(B19-C19)/C19)*100 -> 0
A20: Autres débiteurs divers | B20: 0 | C20: 0 | D20: =IF(C20=0,0,(B20-C20)/C20)*100 -> 0 | E20: 0 | F20: =C20 -> 0 | G20: 0
A21: Comptes permanents non bloqués des établissements et des succursales | B21: 0 | C21: 0 | D21: =IF(C21=0,0,(B21-C21)/C21)*100 -> 0
A22: Comptes de liaison charges et produits | B22: 0 | C22: 0 | D22: =IF(C22=0,0,(B22-C22)/C22)*100 -> 0
A23: Comptes de liaison des sociétés en participation | B23: 0 | C23: 0 | D23: =IF(C23=0,0,(B23-C23)/C23)*100 -> 0
A24: TOTAL BRUT AUTRES CREANCES | B24: =SUM(B14:B23) -> 0 | C24: =SUM(C14:C23) -> 0 | D24: =IF(C24=0,0,(B24-C24)/C24)*100 -> 0 | E24: =SUM(E14:E23) -> 0 | F24: =SUM(F14:F23) -> 0 | G24: =SUM(G14:G23) -> 0
B25: 0 | C25: 0 | D25: =IF(C25=0,0,(B25-C25)/C25)*100 -> 0
A26: Dépréciations des autres créances | B26: 0 | C26: 0 | D26: =IF(C26=0,0,(B26-C26)/C26)*100 -> 0
B27: 0 | C27: 0 | D27: =IF(C27=0,0,(B27-C27)/C27)*100 -> 0
A28: TOTAL NET DE DEPRECIATION | B28: =B24-B26 -> 0 | C28: =C24-C26 -> 0 | D28: =IF(C28=0,0,(B28-C28)/C28)*100 -> 0 | E28: =E24-E26 -> 0 | F28: =F24-F26 -> 0 | G28: =G24-G26 -> 0
A30: Commentaire :
A31: • Justifier toute variation significative.
A32: • Détailler les créances dont le montant est significatif.
A33: • Justifier les créances anciennes.
A34: • Indiquer les événements et circonstances qui ont conduit à la dépréciation et à la reprise.
A35: • Compte transitoire ajustement spécial, indiquer le détail du compte et la durée restant pour l'apurement.

Sheet NOTE 8A
A4: NOTE 8A: TABLEAU D’ETALEMENT DES CHARGES IMMOBILISEES
A6: =_soNom -> Cecotra | E6: =_ExerClos -> Exercice clos le 31/12/2025
A7: =_soId -> 3201810353457 | E7: =_Duree -> Durée (en mois) 12
A9: NOTE 8A
A10: TABLEAU D’ETALEMENT DES CHARGES IMMOBILISEES
A11: Libellés | B11: Frais d'établissement | D11: Charges à repartir sur plusieurs exercices | F11: Primes de remboursement des obligations
A12: Montant global à étaler au 1er janvier 2018
A13: Durée d'étalement retenue
A14: Exercice 2018 | B14: Comptes | C14: Montants | D14: Comptes | E14: Montants | F14: Comptes | G14: Montants
B15: 60... | D15: 60... | F15: 6714
B16: 61... | D16: 61...
B17: 62... | D17: 62...
B18: 63... | D18: 63...
B19: ... | D19: ...
A20: Total exercice 2018
A21: Total exercice 2019
A22: Total exercice 2020
A23: Total exercice 2021
A24: Total exercice 2022
A25: TOTAL GENERAL

Sheet NOTE 9
A4: =_soNom -> Cecotra | B4: =_ExerClos -> Exercice clos le 31/12/2025
A5: =_soId -> 3201810353457 | B5: =_Duree -> Durée (en mois) 12
A7: NOTE 9
A8: TITRES DE PLACEMENT
A9: Libellés | B9: =_ExerFin -> 31/12/2025 | C9: =_ExerFin1 -> 31/12/2024 | D9: Variation en %
A11: Titres de trésor et bons de caisse à court terme | B11: 0 | C11: 0 | D11: =IF(C11=0,0,(B11-C11)/C11)*100 -> 0
A12: Actions | B12: 0 | C12: 0 | D12: =IF(C12=0,0,(B12-C12)/C12)*100 -> 0
A13: Obligations | B13: 0 | C13: 0 | D13: =IF(C13=0,0,(B13-C13)/C13)*100 -> 0
A14: Bons de souscription | B14: 0 | C14: 0 | D14: =IF(C14=0,0,(B14-C14)/C14)*100 -> 0
A15: Titres négociables hors régions | B15: 0 | C15: 0 | D15: =IF(C15=0,0,(B15-C15)/C15)*100 -> 0
A16: Intérêts courus | B16: 0 | C16: 0 | D16: =IF(C16=0,0,(B16-C16)/C16)*100 -> 0
A17: Autres valeurs assimilés | B17: 0 | C17: 0 | D17: =IF(C17=0,0,(B17-C17)/C17)*100 -> 0
A18: TOTAL BRUT TITRES | B18: =SUM(B11:B17) -> 0 | C18: =SUM(C11:C17) -> 0 | D18: =IF(C18=0,0,(B18-C18)/C18)*100 -> 0
D19: =IF(C19=0,0,(B19-C19)/C19)*100 -> 0
A20: Dépréciations des titres | B20: 0 | C20: 0 | D20: =IF(C20=0,0,(B20-C20)/C20)*100 -> 0
D21: =IF(C21=0,0,(B21-C21)/C21)*100 -> 0
A22: TOTAL NET DE DEPRECIATION | B22: =B18-B20 -> 0 | C22: =C18-C20 -> 0 | D22: =IF(C22=0,0,(B22-C22)/C22)*100 -> 0
A23: Commentaires:
A24: • Justifier toute variation significative.
A25: • Pour les titres cotés à une bourse de valeur : indiquer le nombre, le prix unitaire d'acquisition et le cours de la bourse au 31 décembre.
A26: • Faire ressortir les actions ou parts propres et indiquer la date d'acquisition et le nombre de titres détenus.
A27: • Indiquer les événements et circonstances qui ont conduit à la dépréciation et à la reprise.

Sheet NOTE 10
A4: =_soNom -> Cecotra | C4: =_ExerClos -> Exercice clos le 31/12/2025
A5: =_soId -> 3201810353457 | C5: =_Duree -> Durée (en mois) 12
A7: NOTE 10
A8: VALEURS A ENCAISSER
A9: Libellés | B9: =_ExerFin -> 31/12/2025 | C9: =_ExerFin1 -> 31/12/2024 | D9: Variation en %
A10: Effets à encaisser | B10: 0 | C10: 0 | D10: =IF(C10=0,0,(B10-C10)/C10)*100 -> 0
A11: Effets à l'encaissement | B11: 0 | C11: 0 | D11: =IF(C11=0,0,(B11-C11)/C11)*100 -> 0
A12: Chèques à encaisser | B12: 0 | C12: 0 | D12: =IF(C12=0,0,(B12-C12)/C12)*100 -> 0
A13: Chèques à l'encaissement | B13: 0 | C13: 0 | D13: =IF(C13=0,0,(B13-C13)/C13)*100 -> 0
A14: Cartes de crédit à encaisser | B14: 0 | C14: 0 | D14: =IF(C14=0,0,(B14-C14)/C14)*100 -> 0
A15: Autres valeurs à encaisser | B15: 0 | C15: 0 | D15: =IF(C15=0,0,(B15-C15)/C15)*100 -> 0
A16: TOTAL BRUT VALEURS A ENCAISSER | B16: =SUM(B10:B15) -> 0 | C16: =SUM(C10:C15) -> 0 | D16: =IF(C16=0,0,(B16-C16)/C16)*100 -> 0
D17: =IF(C17=0,0,(B17-C17)/C17)*100 -> 0
A18: Dépréciations des valeurs à encaisser | B18: 0 | C18: 0 | D18: =IF(C18=0,0,(B18-C18)/C18)*100 -> 0
D19: =IF(C19=0,0,(B19-C19)/C19)*100 -> 0
A20: TOTAL NET DE DEPRECIATION | B20: =B16-B18 -> 0 | C20: =C16-C18 -> 0 | D20: =IF(C20=0,0,(B20-C20)/C20)*100 -> 0
A21: Commentaires :
A22: • Commenter toute variation significative ;
A23: • Indiquer les événements et circonstances qui ont conduit à la dépréciation et à la reprise.

Sheet NOTE 11
B3: NOTE 11 : BANQUES, CHEQUES POSTAUX ET CHEQUES
B5: =_soNom -> Cecotra | C5: =_ExerClos -> Exercice clos le 31/12/2025
B6: =_soId -> 3201810353457 | C6: =_Duree -> Durée (en mois) 12
B8: NOTE 11
B9: DISPONIBILITES
B10: Libellés | C10: =_ExerFin -> 31/12/2025 | D10: =_ExerFin1 -> 31/12/2024 | E10: Variation
E11: en %
B12: Banques locales | C12: 125136 | D12: 0 | E12: =IF(D12=0,0,(C12-D12)/D12)*100 -> 0
B13: Banques autres états région | C13: 0 | D13: 0 | E13: =IF(D13=0,0,(C13-D13)/D13)*100 -> 0
B14: Banques, dépôt à terme | C14: 0 | D14: 0 | E14: =IF(D14=0,0,(C14-D14)/D14)*100 -> 0
B15: Autres Banques | C15: 0 | D15: 0 | E15: =IF(D15=0,0,(C15-D15)/D15)*100 -> 0
B16: Banques intérêts courus | C16: 0 | D16: 0 | E16: =IF(D16=0,0,(C16-D16)/D16)*100 -> 0
B17: Chèques postaux | C17: 0 | D17: 0 | E17: =IF(D17=0,0,(C17-D17)/D17)*100 -> 0
B18: Autres établissement financiers | C18: 0 | D18: 0 | E18: =IF(D18=0,0,(C18-D18)/D18)*100 -> 0
B19: Etablissement financiers intérêts courus | C19: 0 | D19: 0 | E19: =IF(D19=0,0,(C19-D19)/D19)*100 -> 0
B20: Instruments de trésorerie | C20: 0 | D20: 0 | E20: =IF(D20=0,0,(C20-D20)/D20)*100 -> 0
B21: Caisse | C21: 0 | D21: 0 | E21: =IF(D21=0,0,(C21-D21)/D21)*100 -> 0
B22: Caisse électronique mobile | C22: 0 | D22: 0 | E22: =IF(D22=0,0,(C22-D22)/D22)*100 -> 0
B23: Régies d'avances et virements accréditifs | C23: 0 | D23: 0 | E23: =IF(D23=0,0,(C23-D23)/D23)*100 -> 0
B24: TOTAL BRUT DISPONIBILITES | C24: =SUM(C12:C23) -> 125136 | D24: =SUM(D12:D23) -> 0 | E24: =IF(D24=0,0,(C24-D24)/D24)*100 -> 0
E25: =IF(D25=0,0,(C25-D25)/D25)*100 -> 0
B26: Dépréciations | E26: =IF(D26=0,0,(C26-D26)/D26)*100 -> 0
E27: =IF(D27=0,0,(C27-D27)/D27)*100 -> 0
B28: TOTAL NET DE DEPRECIATION | E28: =IF(D28=0,0,(C28-D28)/D28)*100 -> 0
B29: Commentaires :
B30: • Indiquer la date de rapprochement des comptes bancaires. | C30: 0 | D30: 0
B31: • Indiquer la date d'inventaire de la caisse et des instruments de monnaie électronique.
B32: • Justifier toute variation significative.
B33: • Détailler les instruments de monnaie électronique si le montant est significatif.
B34: • Indiquer les événements et circonstances qui ont conduit à la dépréciation et à la reprise.
B35: NB : Banques et intérêts courus et Etablissement financiers intérêts courus figurent dans cette rubrique en négatif si le compte principal attaché est débiteur.

Sheet NOTE 12
A4: =_soNom -> Cecotra | D4: =_ExerClos -> Exercice clos le 31/12/2025
A5: =_soId -> 3201810353457 | D5: =_Duree -> Durée (en mois) 12
A7: NOTE 12
A8: ECARTS DE CONVERSION
A9: Libellés | B9: Devises | C9: Montant en devises | D9: Cours | E9: Cours | F9: Variation en valeur absolue
D10: UML | E10: UML
D11: Année acquisition | E11: 43100
A12: Ecarts de conversion actif :
A13: détailler les créances et dettes concernées
A16: Ecart de conversion passif : détailler les créances et dettes concernées
A21: Commentaire:
A22:  Faire un commentaire.
A23: TRANSFERTS DE CHARGES
A24: Libellés | B24: =_ExerFin -> 31/12/2025 | C24: =_ExerFin1 -> 31/12/2024 | D24: Variation en %
A25: Transferts de charges d'exploitation :
A26: détailler la nature des charges transférer
A29: Transferts de charges financières : détailler la nature des charges transférer
A35: Commentaire:
A36: • Faire un commentaire

Sheet NOTE 13
B5: =_soNom -> Cecotra | E5: =_ExerClos -> Exercice clos le 31/12/2025
B6: =_soId -> 3201810353457 | E6: =_Duree -> Durée (en mois) 12
B8: NOTE 13
B9: CAPITAL
D10: Valeur nominale des actions ou parts :
B12: Nom et Prénoms | C12: Nationalité | D12: Nature des actions ou parts (ordinaires ou préférences) | E12: Nombre | F12: Montant total | G12: Cessions ou remboursements
G13: en cours
G14: d’exercice
G15: 0
B23: Apporteurs, capital non appelé
B24: TOTAL | F24: =SUM(F15:F22) -> 0 | G24: =SUM(G15:G22) -> 0
B26: Commentaire :
B28: · Indiquer si possible le montant du capital à la constitution.
B29: · Indiquer si possible les dates des AGE et le montant du capital augmenté en cas d’augmentation de capital.
B30: · Indiquer si possible les dates des AGE et le montant du capital diminué en cas de réduction de capital.
B31: · Indiquer les avantages accordés aux actions de préférence.
B32: · Apporteurs, capital non appelé : indiquer le délai restant pour appeler le capital.

Sheet NOTE 14
B4: =_soNom -> Cecotra | C4: =_ExerClos -> Exercice clos le 31/12/2025
B5: =_Duree -> Durée (en mois) 12 | C5: =_Duree -> Durée (en mois) 12
B7: NOTE 14
B8: PRIMES ET RESERVES
B9: Libellés | C9: =_ExerFin -> 31/12/2025 | D9: =_ExerFin1 -> 31/12/2024 | E9: Variation en valeur absolue
B10: Prime d'apport | C10: 0 | D10: 0 | E10: =(C10-D10) -> 0
B11: Primes d'émission | C11: 0 | D11: 0 | E11: =(C11-D11) -> 0
B12: Prime de fusion | C12: 0 | D12: 0 | E12: =(C12-D12) -> 0
B13: Prime de conversion | C13: 0 | D13: 0 | E13: =(C13-D13) -> 0
B14: Autres primes | C14: 0 | D14: 0 | E14: =(C14-D14) -> 0
B15: TOTAL PRIMES | C15: =SUM(C10:C14) -> 0 | D15: =SUM(D10:D14) -> 0 | E15: =(C15-D15) -> 0
E16: =(C16-D16) -> 0
B17: Réserves légales | C17: 0 | D17: 0 | E17: =(C17-D17) -> 0
B18: Réserves statutaires | C18: 0 | D18: 0 | E18: =(C18-D18) -> 0
B19: Réserves de plus-values nettes à long terme | C19: 0 | D19: 0 | E19: =(C19-D19) -> 0
B20: Réserves d’attribution gratuite d’actions au personnel salarié et aux dirigeants | C20: 0 | D20: 0 | E20: =(C20-D20) -> 0
B21: Autres réserves réglementées | C21: 0 | D21: 0 | E21: =(C21-D21) -> 0
B22: TOTAL RESERVES INDISPONIBLES | C22: =SUM(C17:C21) -> 0 | D22: =SUM(D17:D21) -> 0 | E22: =(C22-D22) -> 0
E23: =(C23-D23) -> 0
B24: Réserves libres | C24: 0 | D24: 0 | E24: =(C24-D24) -> 0
E25: =(C25-D25) -> 0
B26: Report à nouveau | C26: 29907501 | D26: 0 | E26: =(C26-D26) -> 29907501
B27: Commentaires:
B28: • Indiquer les dates de l'AGE qui a décidé des primes d'apport, d'émission de fusion.
B29: • Indiquer le détail des réserves libres.
B30: • Indiquer le montant restant à doter et le taux de dotation de la réserve légale.
B31: • Indiquer la date de l'AGO qui justifie la variation des réserves et du report à nouveau.

Sheet NOTE 15A
A4: =_soNom -> Cecotra | E4: =_ExerClos -> Exercice clos le 31/12/2025
A5: =_soId -> 3201810353457 | E5: =_Duree -> Durée (en mois) 12
A7: NOTE 15 A
A8: TOTAL SUBVENTIONS ET PROVISIONS REGLEMENTEES
A9: Libellés | B9: 0 | C9: 0 | D9: =_ExerFin1 -> 31/12/2024 | E9: Variation en valeur absolue | F9: Variation en % | G9: Régime fiscal | H9: Echéances
A10: État | B10: 0 | C10: 0 | D10: 0 | E10: =(C10-D10) -> 0 | F10: =IF(D10=0,0,(C10-D10)/D10)*100 -> 0
A11: Régions | B11: 0 | C11: 0 | D11: 0 | E11: =(C11-D11) -> 0 | F11: =IF(D11=0,0,(C11-D11)/D11)*100 -> 0
A12: Départements | B12: 0 | C12: 0 | D12: 0 | E12: =(C12-D12) -> 0 | F12: =IF(D12=0,0,(C12-D12)/D12)*100 -> 0
A13: Communes et collectivités publiques décentralisées | B13: 0 | C13: 0 | D13: 0 | E13: =(C13-D13) -> 0 | F13: =IF(D13=0,0,(C13-D13)/D13)*100 -> 0
A14: Entités publiques ou mixtes | B14: 0 | C14: 0 | D14: 0 | E14: =(C14-D14) -> 0 | F14: =IF(D14=0,0,(C14-D14)/D14)*100 -> 0
A15: Entités et organismes privés | B15: 0 | C15: 0 | D15: 0 | E15: =(C15-D15) -> 0 | F15: =IF(D15=0,0,(C15-D15)/D15)*100 -> 0
A16: Organismes internationaux | B16: 0 | C16: 0 | D16: 0 | E16: =(C16-D16) -> 0 | F16: =IF(D16=0,0,(C16-D16)/D16)*100 -> 0
A17: Autres | C17: 0 | D17: 0 | E17: =(C17-D17) -> 0 | F17: =IF(D17=0,0,(C17-D17)/D17)*100 -> 0
A18: TOTAL SUBVENTIONS | C18: 0 | D18: 0 | E18: =(C18-D18) -> 0 | F18: =IF(D18=0,0,(C18-D18)/D18)*100 -> 0
B19: 0 | C19: 0 | E19: =(C19-D19) -> 0 | F19: =IF(D19=0,0,(C19-D19)/D19)*100 -> 0
A20: Amortissements dérogatoires | B20: 0 | C20: 0 | E20: =(C20-D20) -> 0 | F20: =IF(D20=0,0,(C20-D20)/D20)*100 -> 0
A21: Plus-value de cession à réinvestir | B21: 0 | C21: 0 | D21: 0 | E21: =(C21-D21) -> 0 | F21: =IF(D21=0,0,(C21-D21)/D21)*100 -> 0
A22: Provision spéciale de réévaluation | B22: 0 | C22: 0 | D22: 0 | E22: =(C22-D22) -> 0 | F22: =IF(D22=0,0,(C22-D22)/D22)*100 -> 0
A23: Provisions réglementées relatives aux immobilisations | B23: 0 | C23: 0 | D23: 0 | E23: =(C23-D23) -> 0 | F23: =IF(D23=0,0,(C23-D23)/D23)*100 -> 0
A24: Provisions réglementés relatives aux stocks | C24: 0 | D24: 0 | E24: =(C24-D24) -> 0 | F24: =IF(D24=0,0,(C24-D24)/D24)*100 -> 0
A25: Provisions pour investissement | C25: 0 | D25: 0 | E25: =(C25-D25) -> 0 | F25: =IF(D25=0,0,(C25-D25)/D25)*100 -> 0
A26: Autres provisions et fonds réglementées | B26: 0 | C26: 0 | D26: 0 | E26: =(C26-D26) -> 0 | F26: =IF(D26=0,0,(C26-D26)/D26)*100 -> 0
A27: TOTAL PROVISIONS REGLEMENTEES | B27: 0 | C27: 0 | D27: 0 | E27: =(C27-D27) -> 0 | F27: =IF(D27=0,0,(C27-D27)/D27)*100 -> 0
B28: 0 | C28: 0 | D28: 0 | E28: =(C28-D28) -> 0
A29: TOTAL SUBVENTIONS ET | B29: 0 | C29: 0 | D29: =+D18+D27 -> 0 | E29: =(C29-D29) -> 0 | F29: =IF(D29=0,0,(C29-D29)/D29)*100 -> 0
A30: PROVISIONS REGLEMENTEES
B31: 0 | C31: 0
A32: Commentaire: | B32: 0 | C32: 0
A33: Indiquer pour la subvention la date d’octroi, la nature, les obligations éventuelles. Pour les provisions réglementées, indiquer le texte de référence, les obligations. Commenter toute variation significative.
B34: 0 | C34: 0
B35: 0 | C35: 0
B36: 0 | C36: 0
B37: 0 | C37: 0
B38: 0 | C38: 0

Sheet NOTES 15B
A4: =_soNom -> Cecotra | E4: =_ExerClos -> Exercice clos le 31/12/2025
A5: =_soId -> 3201810353457 | E5: =_Duree -> Durée (en mois) 12
A7: NOTE 15 B
A8: AUTRES FONDS PROPRES (1)
A9: Libellés | B9: NOTE | C9: =_ExerFin -> 31/12/2025 | D9: =_ExerFin1 -> 31/12/2024 | E9: Variation en valeur absolue | F9: Variation en % | G9: Echéances
A10: Titres participatifs | E10: =C10-D10 -> 0 | F10: =IF(D10=0,0,(C10-D10)/D10)*100 -> 0
A11: Avances conditionnées (1) | E11: =C11-D11 -> 0 | F11: =IF(D11=0,0,(C11-D11)/D11)*100 -> 0
A12: Titres subordonnés à durée indéterminée (T.S.D.I.) | E12: =C12-D12 -> 0 | F12: =IF(D12=0,0,(C12-D12)/D12)*100 -> 0
A13: Obligations remboursables en actions (O.R.A.) | E13: =C13-D13 -> 0 | F13: =IF(D13=0,0,(C13-D13)/D13)*100 -> 0
A14: Autres | E14: =C14-D14 -> 0 | F14: =IF(D14=0,0,(C14-D14)/D14)*100 -> 0
A15: TOTAL AUTRES FONDS PROPRES | C15: =SUM(C10:C14) -> 0 | D15: =SUM(D10:D14) -> 0 | E15: =C15-D15 -> 0 | F15: =IF(D15=0,0,(C15-D15)/D15)*100 -> 0
A16: Commentaire :
A17: (1) Le cas échéant, une rubrique "Autres fonds propres" (montant des émissions de titres participatifs, avances conditionnées, ...) sur une ligne séparée est intercalée entre les rubriques "TOTAL CAPITAUX PROPRES ET RESSOURCES ASSIMILEES" et "emprunts et dettes financières" si le montant des autres fonds propres est significatif.
A18: Commentaires :
A19: * Justifier l'inscription de ces dettes dans une rubrique spécifique du passif du bilan "autres fonds propres" (faible probabilité de remboursement, absence d’échéancier…;
A20: *Justifier le caractère significatif du montant total de cette rubrique Commenter toute variation significative.

Sheet NOTE 16A
A3: =_soNom -> Cecotra | E3: =_ExerClos -> Exercice clos le 31/12/2025
A4: =_soId -> 3201810353457 | E4: =_Duree -> Durée (en mois) 12
A5: NOTE 16A
A6: Libellés | B6: =_ExerFin -> 31/12/2025 | C6: =_ExerFin1 -> 31/12/2024 | D6: Variation en valeur absolue | E6: Variation en % | F6: Dettes à un an au plus | G6: Dettes à plus d’un an et à deux ans au plus | H6: Dettes à plus de deux ans
A7: Emprunts obligataires | B7: 0 | C7: 0 | D7: =(B7-C7) -> 0 | E7: =IF(C7=0,0,(B7-C7)/C7)*100 -> 0
A8: Emprunts et dettes auprès des établissements de crédit | B8: 0 | C8: 0 | D8: =(B8-C8) -> 0 | E8: =IF(C8=0,0,(B8-C8)/C8)*100 -> 0 | F8: =0 -> 0 | H8: =B8-G8 -> 0
A9: Avances reçues de l’Etat | B9: 0 | C9: 0 | D9: =(B9-C9) -> 0 | E9: =IF(C9=0,0,(B9-C9)/C9)*100 -> 0
A10: Avances reçues et comptes courants bloqués | B10: 0 | C10: 0 | D10: =(B10-C10) -> 0 | E10: =IF(C10=0,0,(B10-C10)/C10)*100 -> 0
A11: Dépôts et cautionnements reçus | B11: 0 | C11: 0 | D11: =(B11-C11) -> 0 | E11: =IF(C11=0,0,(B11-C11)/C11)*100 -> 0
A12: Intérêt courus | B12: 0 | C12: 0 | D12: =(B12-C12) -> 0 | E12: =IF(C12=0,0,(B12-C12)/C12)*100 -> 0
A13: Avances assorties de conditions particulières | B13: 0 | C13: 0 | D13: =(B13-C13) -> 0 | E13: =IF(C13=0,0,(B13-C13)/C13)*100 -> 0
A14: Autres emprunts et dettes | B14: 0 | C14: 0 | D14: =(B14-C14) -> 0 | E14: =IF(C14=0,0,(B14-C14)/C14)*100 -> 0 | G14: 0 | H14: =C14 -> 0
A15: Dettes liées à des participations | B15: 0 | C15: 0 | D15: =(B15-C15) -> 0 | E15: =IF(C15=0,0,(B15-C15)/C15)*100 -> 0
A16: Comptes permanents bloqués des établissements et succursales | B16: 0 | C16: 0 | D16: =(B16-C16) -> 0 | E16: =IF(C16=0,0,(B16-C16)/C16)*100 -> 0
A17: TOTAL EMPRUNTS ET DETTES FINANCIERES | B17: =SUM(B7:B16) -> 0 | C17: =SUM(C7:C16) -> 0 | D17: =SUM(D7:D16) -> 0 | E17: =IF(C17=0,0,(B17-C17)/C17)*100 -> 0 | F17: =SUM(F7:F16) -> 0 | G17: =SUM(G7:G16) -> 0 | H17: =SUM(H7:H16) -> 0
A19: Crédit-bail immobilier | B19: 0 | C19: 0 | E19: =IF(C19=0,0,(B19-C19)/C19)*100 -> 0
A20: Crédit-bail mobilier | B20: 0 | C20: 0 | E20: =IF(C20=0,0,(B20-C20)/C20)*100 -> 0
A21: Location-vente | B21: 0 | C21: 0 | E21: =IF(C21=0,0,(B21-C21)/C21)*100 -> 0
A22: Intérêts courus | B22: 0 | C22: 0 | E22: =IF(C22=0,0,(B22-C22)/C22)*100 -> 0
A23: Autres dettes de location acquisition | B23: 0 | C23: 0 | E23: =IF(C23=0,0,(B23-C23)/C23)*100 -> 0
A24: TOTAL DETTES DE LOCATION ACQUISITION | B24: =SUM(B19:B23) -> 0 | C24: =SUM(C19:C23) -> 0 | D24: =(B24-C24) -> 0 | E24: =IF(C24=0,0,(B24-C24)/C24)*100 -> 0 | F24: =SUM(F19:F23) -> 0 | G24: =SUM(G19:G23) -> 0
A26: Provisions pour litiges | B26: 0 | C26: 0 | D26: =B26-C26 -> 0 | E26: =IF(C26=0,0,(B26-C26)/C26)*100 -> 0
A27: Provisions pour garantie donnés aux clients | B27: 0 | C27: 0 | E27: =IF(C27=0,0,(B27-C27)/C27)*100 -> 0
A28: Provisions pour pertes sur marchés à achèvement futur | B28: 0 | C28: 0 | E28: =IF(C28=0,0,(B28-C28)/C28)*100 -> 0
A29: Provisions pour pertes de change | B29: 0 | C29: 0 | E29: =IF(C29=0,0,(B29-C29)/C29)*100 -> 0
A30: Provisions pour impôts | B30: 0 | C30: 0 | E30: =IF(C30=0,0,(B30-C30)/C30)*100 -> 0
A31: Provisions pour pensions et obligations assimilées | B31: 0 | C31: 0 | E31: =IF(C31=0,0,(B31-C31)/C31)*100 -> 0
A32: Actif du régime de retraite | B32: 0 | C32: 0 | E32: =IF(C32=0,0,(B32-C32)/C32)*100 -> 0
A33: Provisions pour restructuration | B33: 0 | C33: 0 | E33: =IF(C33=0,0,(B33-C33)/C33)*100 -> 0
A34: Provisions pour amendes et pénalités | B34: 0 | C34: 0 | E34: =IF(C34=0,0,(B34-C34)/C34)*100 -> 0
A35: Provisions de propre assureur | B35: 0 | C35: 0 | E35: =IF(C35=0,0,(B35-C35)/C35)*100 -> 0
A36: Provisions pour démantèlement et remise en état | B36: 0 | C36: 0 | E36: =IF(C36=0,0,(B36-C36)/C36)*100 -> 0
A37: Provisions de droits à déduction | B37: 0 | C37: 0 | E37: =IF(C37=0,0,(B37-C37)/C37)*100 -> 0
A38: Autres provisions | B38: 0 | C38: 0 | E38: =IF(C38=0,0,(B38-C38)/C38)*100 -> 0
A39: TOTAL PROVISIONS POUR RISQUES ET CHARGES | B39: =SUM(B26:B38) -> 0 | C39: =SUM(C26:C38) -> 0 | D39: =B39-C39 -> 0 | E39: =IF(C39=0,0,(B39-C39)/C39)*100 -> 0
A40: Commentaire :

Sheet NOTE 16B
A5: =_soNom -> Cecotra | B5: =_ExerClos -> Exercice clos le 31/12/2025
A6: =_soId -> 3201810353457 | B6: =_Duree -> Durée (en mois) 12
A7: NOTE 16B
A8: ENGAGEMENTS DE RETRAITE ET AVANTAGES ASSIMILES
A9: HYPOTHESES ACTUARIELLES
A10: Libellés | B10: =_ExerFin -> 31/12/2025 | C10: =_ExerFin1 -> 31/12/2024
A11: Taux d'augmentation des salaires
A12: Taux d'actualisation
A13: Taux d'inflation
A14: Probabilité d'être présent dans l'entité à la date de départ à la retraite (expérience passée)
A15: Probabilité d'être en vie à l'âge de départ à la retraite (table de mortalité)
A16: Taux de rendement effectif des actifs du régime
A17: Commentaire :
A18: • Commenter les variations d'hypothèses actuarielles utilisées pour le calcul des engagements de retraite et avantages assimilés.
A20: VARIATION DE LA VALEUR DE L'ENGAGEMENT DE RETRAITE AU COURS DE L'EXERCICE
A21: Libellés | B21: =_ExerFin -> 31/12/2025 | C21: =_ExerFin1 -> 31/12/2024
A22: Obligation au titre des engagements de retraite à l'ouverture
A23: Coût des services rendus au cours de l'exercice
A24: Coût financier
A25: Pertes actuarielles / (gain)
A26: Prestations payées au cours de l'exercice
A27: Coût des services passés
A28: Obligation au titre des engagements de retraite à la clôture
A30: Commentaire :
A31: • Indiquer le montant de la charge par nature comptabilisée au cours de l'exercice
A32: ANALYSE DE SENSIBILITE DES HYPOTHESES ACTUARIELLES
A33: Libellés | B33: =_ExerFin -> 31/12/2025 | D33: =_ExerFin1 -> 31/12/2024
B34: Augmentation | C34: Diminution | D34: Augmentation | E34: Diminution
A35: Taux d'actualisation
A36: (variation de ...%)
A37: Taux de progression des salaires (variation de ...%)
A38: Taux de départ du personnel (variation de ...%)
A40: Commentaire :
A41: • Indiquer l’impact des variations obtenues sur le montant des engagements de retraite.
A42: • clôture et leur base de détermination.

Sheet NOTE 16B bis
A5: =_soNom -> Cecotra | C5: =_ExerClos -> Exercice clos le 31/12/2025
A6: =_soId -> 3201810353457 | C6: =_Duree -> Durée (en mois) 12
A8: NOTE 16B bis
A10: ENGAGEMENTS DE RETRAITE ET AVANTAGES ASSIMILES
A11: ACTIF/PASSIF NET COMPTABILISE AU TITRE DES REGIMES FINANCES
A12: Libellés | B12: =_ExerFin -> 31/12/2025 | C12: =_ExerFin1 -> 31/12/2024
A13: Valeur actuelle de l'obligation résultant de régimes financés
A14: Valeur actuelle des actifs affectés aux plans de retraite
A15: Excédent / Déficit de régime | B15: =+B13+B14 -> 0 | C15: =+C13+C14 -> 0
A16: Commentaire :
A17: • Indiquer le montant comptabilisé au passif (ou actif) à la clôture de l'exercice
A19: VALEUR ACTUELLE DES ACTIFS DU REGIME
A20: Libellés | B20: =_ExerFin -> 31/12/2025 | D20: =_ExerFin1 -> 31/12/2024
B21: Rendement attendu | C21: Juste valeur des actifs | D21: Rendement attendu | E21: Juste valeur des actifs
A22: Actions
A23: Obligations
A24: Autres
A25: Total | B25: =B22+B23+B24 -> 0 | C25: =C22+C23+C24 -> 0 | D25: =D22+D23+D24 -> 0 | E25: =E22+E23+E24 -> 0
A27: Commentaires :
A28: • Expliquer comment les taux de rendement par catégorie d’actifs et global ont été déterminés
A29: • Indiquer le montant des rendements réels des actifs affectés aux plans en N et N-1
A30: • Indiquer….

Sheet NOTE 16C
A6: =_soNom -> Cecotra | B6: =_ExerClos -> Exercice clos le 31/12/2025
A7: =_soId -> 3201810353457 | B7: =_Duree -> Durée (en mois) 12
A10: NOTE 16C
A11: ACTIFS ET PASSIFS EVENTUELS
A12: Libellés | B12: =_ExerFin -> 31/12/2025 | C12: =_ExerFin1 -> 31/12/2024
A13: Actif éventuel
A14: Litiges
A15: .............
A16: .............
A17: Passif éventuel
A18: Litiges
A19: .............
A20: .............
A21: Commentaire:
A22: • Décrire les principales caractéristiques des actifs / passifs éventuels, l’horizon de temps auquel les encaissements / décaissements sont attendus et les éventuels remboursements à percevoir.

Sheet NOTE 17
A4: =_soNom -> Cecotra | D4: =_ExerClos -> Exercice clos le 31/12/2025
A5: =_soId -> 3201810353457 | D5: =_Duree -> Durée (en mois) 12
A7: NOTE 17
A8: FOURNISSEURS D'EXPLOITATION
A9: Libellés | B9: =_ExerFin -> 31/12/2025 | C9: =_ExerFin1 -> 31/12/2024 | D9: Variation en % | E9: Dettes à un an au plus | F9: Dettes à plus d'un an et à deux ans au plus | G9: Dettes à plus de deux ans
A10: Fournisseurs dettes en compte (hors groupe) | B10: 0 | C10: 0 | D10: =IF(C10=0,0,(B10-C10)/C10)*100 -> 0 | E10: =B10 -> 0 | G10: 0
A11: Fournisseurs effets à payer (hors groupe) | B11: 0 | C11: 0 | D11: =IF(C11=0,0,(B11-C11)/C11)*100 -> 0
A12: Fournisseurs, dettes et effets à payer groupe | B12: 0 | C12: 0 | D12: =IF(C12=0,0,(B12-C12)/C12)*100 -> 0
A13: Fournisseurs factures non parvenues (hors groupe) | B13: 0 | C13: 0 | D13: =IF(C13=0,0,(B13-C13)/C13)*100 -> 0
A14: Fournisseurs factures non parvenues groupe | B14: 0 | C14: 0 | D14: =IF(C14=0,0,(B14-C14)/C14)*100 -> 0
A15: TOTAL FOURNISSEURS | B15: =SUM(B10:B14) -> 0 | C15: =SUM(C10:C14) -> 0 | D15: =IF(C15=0,0,(B15-C15)/C15)*100 -> 0 | E15: =SUM(E10:E14) -> 0 | F15: =SUM(F10:F14) -> 0 | G15: =SUM(G10:G14) -> 0
A17: Fournisseurs, avances et acomptes (hors groupe) | B17: 0 | C17: 0 | D17: =IF(C17=0,0,(B17-C17)/C17)*100 -> 0
A18: Fournisseurs, avances et acomptes groupe | B18: 0 | C18: 0 | D18: =IF(C18=0,0,(B18-C18)/C18)*100 -> 0
A19: Autres fournisseurs débiteurs | B19: 0 | C19: 0 | D19: =IF(C19=0,0,(B19-C19)/C19)*100 -> 0
A20: TOTAL FOURNISSEURS DEBITEURS | B20: =SUM(B17:B19) -> 0 | C20: =SUM(C17:C19) -> 0 | D20: =IF(C20=0,0,(B20-C20)/C20)*100 -> 0 | E20: =SUM(E17:E19) -> 0 | F20: =SUM(F17:F19) -> 0 | G20: =SUM(G17:G19) -> 0
A21: Commentaires:

Sheet NOTE 18
A4: =_soNom -> Cecotra | F4: =_ExerClos -> Exercice clos le 31/12/2025
A5: =_soId -> 3201810353457 | F5: =_Duree -> Durée (en mois) 12
A7: NOTE 18
A8: DETTES FISCALES ET SOCIALES
A9: Libellés | B9: =_ExerFin -> 31/12/2025 | C9: =_ExerFin1 -> 31/12/2024 | D9: Variation en valeur absolue | E9: Variation en % | F9: Dettes à un an au plus | G9: Dettes à plus d'un | H9: Dettes à plus de deux ans
G10: an et à deux ans au plus
A11: Personnel avances et acomptes | B11: 0 | C11: 0 | D11: =B11-C11 -> 0 | E11: =IF(C11=0,0,(B11-C11)/C11)*100 -> 0 | F11: =B11 -> 0
A12: Personnel rémunérations dues | B12: 0 | C12: 0 | D12: =B12-C12 -> 0 | E12: =IF(C12=0,0,(B12-C12)/C12)*100 -> 0 | F12: =B12 -> 0
A13: Autres personnel | B13: 0 | C13: 0 | D13: =B13-C13 -> 0 | E13: =IF(C13=0,0,(B13-C13)/C13)*100 -> 0 | F13: =B13 -> 0
A14: Caisse de sécurité sociale | B14: 0 | C14: 0 | D14: =B14-C14 -> 0 | E14: =IF(C14=0,0,(B14-C14)/C14)*100 -> 0 | F14: =B14 -> 0 | H14: 0
A15: Caisse de retraite | B15: 0 | C15: 0 | D15: =B15-C15 -> 0 | E15: =IF(C15=0,0,(B15-C15)/C15)*100 -> 0 | F15: =B15 -> 0
A16: Autres organisme sociaux | B16: 0 | C16: 0 | D16: =B16-C16 -> 0 | E16: =IF(C16=0,0,(B16-C16)/C16)*100 -> 0 | F16: =B16 -> 0
A17: TOTAL DETTES SOCIALES | B17: =SUM(B11:B16) -> 0 | C17: =SUM(C11:C16) -> 0 | D17: =B17-C17 -> 0 | E17: =IF(C17=0,0,(B17-C17)/C17)*100 -> 0 | F17: =SUM(F11:F16) -> 0 | G17: =SUM(G11:G16) -> 0 | H17: =SUM(H11:H16) -> 0
A19: Etat, impôts sur les bénéfices | B19: 6861600 | C19: 0 | D19: =B19-C19 -> 6861600 | E19: =IF(C19=0,0,(B19-C19)/C19)*100 -> 0 | F19: =B19 -> 6861600 | H19: 0
A20: Etat, impôts et taxes | B20: 0 | C20: 0 | D20: =B20-C20 -> 0 | E20: =IF(C20=0,0,(B20-C20)/C20)*100 -> 0 | F20: =B20 -> 0 | H20: 0
A21: Etat, TVA | B21: 1100590 | C21: 0 | D21: =B21-C21 -> 1100590 | E21: =IF(C21=0,0,(B21-C21)/C21)*100 -> 0 | F21: =B21 -> 1100590
A22: Etat, impôts retenus à la source | B22: 0 | C22: 0 | D22: =B22-C22 -> 0 | E22: =IF(C22=0,0,(B22-C22)/C22)*100 -> 0 | F22: =B22 -> 0
A23: Autres dettes Etat | B23: 0 | C23: 0 | D23: =B23-C23 -> 0 | E23: =IF(C23=0,0,(B23-C23)/C23)*100 -> 0 | F23: =B23 -> 0
A24: TOTAL DETTES FISCALES | B24: =SUM(B18:B23) -> 7962190 | C24: =SUM(C18:C23) -> 0 | D24: =B24-C24 -> 7962190 | E24: =IF(C24=0,0,(B24-C24)/C24)*100 -> 0 | F24: =SUM(F18:F23) -> 7962190 | G24: =SUM(G18:G23) -> 0 | H24: =SUM(H18:H23) -> 0
E25: =IF(C25=0,0,(B25-C25)/C25)*100 -> 0
A26: TOTAL DETTES SOCIALES ET FISCALES | B26: =B17+B24 -> 7962190 | C26: =C17+C24 -> 0 | D26: =B26-C26 -> 7962190 | E26: =IF(C26=0,0,(B26-C26)/C26)*100 -> 0 | F26: =F17+F24 -> 7962190 | G26: =G17+G24 -> 0 | H26: =H17+H24 -> 0
A28: Commentaires:
A29:  Commenter toute variation significative.
A30:  Commenter les dettes anciennes.

Sheet NOTE 19
A4: =_soNom -> Cecotra | E4: =_ExerClos -> Exercice clos le 31/12/2025
A5: =_soId -> 3201810353457 | E5: =_Duree -> Durée (en mois) 12
A6: NOTE 19
A7: AUTRES DETTES ET PROVISIONS POUR RISQUES A COURT TERME
A8: Libellés | B8: =_ExerFin -> 31/12/2025 | C8: =_ExerFin1 -> 31/12/2024 | D8: Variation en valeur absolue | E8: Variation en % | F8: Dettes à un an au plus | G8: Dettes à plus d'un an et à deux ans au plus | H8: Dettes à plus de deux ans
A10: Organismes internationaux | B10: 0 | C10: 0 | D10: =B10-C10 -> 0 | E10: =IF(C10=0,0,(B10-C10)/C10)*100 -> 0
A11: Apporteurs, opérations sur le capital | B11: 0 | C11: 0 | D11: =B11-C11 -> 0 | E11: =IF(C11=0,0,(B11-C11)/C11)*100 -> 0
A12: Associés, compte courant | B12: 0 | C12: 0 | D12: =B12-C12 -> 0 | E12: =IF(C12=0,0,(B12-C12)/C12)*100 -> 0
A13: Associés dividendes à payer | B13: 0 | C13: 0 | D13: =B13-C13 -> 0 | E13: =IF(C13=0,0,(B13-C13)/C13)*100 -> 0
A14: Groupe, comptes courants | B14: 0 | C14: 0 | D14: =B14-C14 -> 0 | E14: =IF(C14=0,0,(B14-C14)/C14)*100 -> 0
A15: Autres dettes associés | B15: 0 | C15: 0 | D15: =B15-C15 -> 0 | E15: =IF(C15=0,0,(B15-C15)/C15)*100 -> 0
A16: TOTAL DETTES ASSOCIES | B16: =SUM(B10:B15) -> 0 | C16: =SUM(C10:C15) -> 0 | D16: =B16-C16 -> 0 | E16: =IF(C16=0,0,(B16-C16)/C16)*100 -> 0 | F16: =SUM(F10:F15) -> 0 | G16: =SUM(G10:G15) -> 0 | H16: =SUM(H10:H15) -> 0
A17: Créditeurs divers | B17: 0 | C17: 0 | D17: =B17-C17 -> 0 | E17: =IF(C17=0,0,(B17-C17)/C17)*100 -> 0
A18: Obligataires | B18: 0 | C18: 0 | D18: =B18-C18 -> 0 | E18: =IF(C18=0,0,(B18-C18)/C18)*100 -> 0
A19: Rémunérations d'administrateurs | B19: 0 | C19: 0 | D19: =B19-C19 -> 0 | E19: =IF(C19=0,0,(B19-C19)/C19)*100 -> 0
A20: Compte d'affacturage et de titrisation | B20: 0 | C20: 0 | D20: =B20-C20 -> 0 | E20: =IF(C20=0,0,(B20-C20)/C20)*100 -> 0
A21: Versements restant à effectuer sur titres de placement non libérés | B21: 0 | C21: 0 | D21: =B21-C21 -> 0 | E21: =IF(C21=0,0,(B21-C21)/C21)*100 -> 0
A22: Compte transitoire ajustement spécial lié à la révision du SYSCOHADA | B22: 0 | C22: 0 | D22: =B22-C22 -> 0 | E22: =IF(C22=0,0,(B22-C22)/C22)*100 -> 0
A23: Autres créditeurs divers | B23: 0 | C23: 0 | D23: =B23-C23 -> 0 | E23: =IF(C23=0,0,(B23-C23)/C23)*100 -> 0
A24: TOTAL CREDITEURS DIVERS | B24: 0 | C24: 0 | D24: =B24-C24 -> 0 | E24: =IF(C24=0,0,(B24-C24)/C24)*100 -> 0 | F24: =SUM(F17:F23) -> 0 | G24: =SUM(G17:G23) -> 0 | H24: =SUM(H17:H23) -> 0
A25: Comptes permanents non bloqués des établissements et des succursales | B25: 0 | C25: 0 | D25: =B25-C25 -> 0 | E25: =IF(C25=0,0,(B25-C25)/C25)*100 -> 0
A26: Comptes de liaison charges et produits | B26: 0 | C26: 0 | D26: =B26-C26 -> 0 | E26: =IF(C26=0,0,(B26-C26)/C26)*100 -> 0
A27: Comptes de liaison des sociétés en participation | B27: 0 | C27: 0 | D27: =B27-C27 -> 0 | E27: =IF(C27=0,0,(B27-C27)/C27)*100 -> 0
A28: TOTAL COMPTES DE LIAISON | B28: 0 | C28: 0 | D28: =B28-C28 -> 0 | E28: =IF(C28=0,0,(B28-C28)/C28)*100 -> 0 | F28: =SUM(F25:F27) -> 0 | G28: =SUM(G25:G27) -> 0 | H28: =SUM(H25:H27) -> 0
B29: 0 | C29: 0 | D29: =B29-C29 -> 0 | E29: =IF(C29=0,0,(B29-C29)/C29)*100 -> 0
A30: TOTAL AUTRES DETTES | B30: =+B16+B24+B28 -> 0 | C30: =+C16+C24+C28 -> 0 | D30: =B30-C30 -> 0 | E30: =IF(C30=0,0,(B30-C30)/C30)*100 -> 0 | F30: =+F16+F24+F28 -> 0 | G30: =+G16+G24+G28 -> 0 | H30: =+H16+H24+H28 -> 0
A32: Provisions pour risques à court terme (voir note 28)
A33: Commentaires :
A34: • Commenter toute variation significative.
A35: • Indiquer le taux de rémunération si compte courant rémunéré.
A36: • Commenter les dettes anciennes.
A37: • Compte transitoire ajustement spécial, indiquer le détail du compte et la durée restant pour l'apurement.

Sheet NOTE 20
A5: =_soNom -> Cecotra | C5: =_ExerClos -> Exercice clos le 31/12/2025
A6: =_soId -> 3201810353457 | C6: =_Duree -> Durée (en mois) 12
A8: NOTE 20
A9: BANQUES, CREDIT D'ESCOMPTE ET DE TRESORERIE
A10: Libellés | B10: =_ExerFin -> 31/12/2025 | C10: =_ExerFin1 -> 31/12/2024 | D10: Variation en %
A12: Escomptes de crédit de campagne | B12: 0 | C12: 0 | D12: =IF(C12=0,0,(B12-C12)/C12)*100 -> 0
A13: Escomptes de crédit ordinaires | D13: =IF(C13=0,0,(B13-C13)/C13)*100 -> 0
A14: TOTAL: BANQUES, CREDITS | B14: =+B12+B13 -> 0 | C14: =+C12+C13 -> 0 | D14: =IF(C14=0,0,(B14-C14)/C14)*100 -> 0
A15: D'ESCOMPTE ET DE TRESORERIE
B16: 0 | C16: 0
A17: Banques locales | B17: 0 | C17: 0 | D17: =IF(C17=0,0,(B17-C17)/C17)*100 -> 0
A18: Banques autres états région | B18: 0 | C18: 0 | D18: =IF(C18=0,0,(B18-C18)/C18)*100 -> 0
A19: Autres Banques | B19: 0 | C19: 0 | D19: =IF(C19=0,0,(B19-C19)/C19)*100 -> 0
A20: Banques intérêts courus | B20: 0 | C20: 0 | D20: =IF(C20=0,0,(B20-C20)/C20)*100 -> 0
A21: Crédit de trésorerie | D21: =IF(C21=0,0,(B21-C21)/C21)*100 -> 0
A22: TOTAL: BANQUES, CREDITS DE TRESORERIE | B22: =SUM(B17:B21) -> 0 | C22: =SUM(C17:C21) -> 0 | D22: =IF(C22=0,0,(B22-C22)/C22)*100 -> 0
A24: TOTAL GENERAL | B24: =+B14+B22 -> 0 | C24: =+C14+C22 -> 0 | D24: =IF(C24=0,0,(B24-C24)/C24)*100 -> 0
A25: Commentaires:
A26: • Commenter toute variation significative.
A27: • Indiquer le nom de l'organisme les conditions de crédit, le taux d'intérêt, la durée du crédit.
A28: NB : Banques et intérêts courus figure dans cette rubrique si le compte principal attaché est créditeur.

Sheet NOTE 21
A6: =_soNom -> Cecotra | B6: =_ExerClos -> Exercice clos le 31/12/2025
A7: =_soId -> 3201810353457 | B7: =_Duree -> Durée (en mois) 12
A9: NOTE 21
A10: CHIFFRE D’AFFAIRES et AUTRES PRODUITS
A11: Libellés | B11: =_ExerFin -> 31/12/2025 | C11: =_ExerFin1 -> 31/12/2024 | D11: Variation en %
A13: Ventes dans la région | B13: 0 | C13: 0 | D13: =IF(C13=0,0,(B13-C13)/C13)*100 -> 0
A14: Ventes hors région | B14: 0 | C14: 0 | D14: =IF(C14=0,0,(B14-C14)/C14)*100 -> 0
A15: Ventes groupe | B15: 0 | C15: 0 | D15: =IF(C15=0,0,(B15-C15)/C15)*100 -> 0
A16: Ventes sur internet | B16: 0 | C16: 0 | D16: =IF(C16=0,0,(B16-C16)/C16)*100 -> 0
A17: TOTAL : VENTES MARCHANDISES | B17: =SUM(B13:B16) -> 0 | C17: =SUM(C13:C16) -> 0 | D17: =IF(C17=0,0,(B17-C17)/C17)*100 -> 0
D18: =IF(C18=0,0,(B18-C18)/C18)*100 -> 0
A19: Ventes dans la région | B19: 0 | C19: 0 | D19: =IF(C19=0,0,(B19-C19)/C19)*100 -> 0
A20: Ventes hors région | B20: 0 | C20: 0 | D20: =IF(C20=0,0,(B20-C20)/C20)*100 -> 0
A21: Ventes groupe | B21: 0 | C21: 0 | D21: =IF(C21=0,0,(B21-C21)/C21)*100 -> 0
A22: Ventes sur internet | B22: 0 | C22: 0 | D22: =IF(C22=0,0,(B22-C22)/C22)*100 -> 0
A23: TOTAL : VENTES DE PRODUITS FABRIQUES | B23: 0 | C23: 0 | D23: =IF(C23=0,0,(B23-C23)/C23)*100 -> 0
D24: =IF(C24=0,0,(B24-C24)/C24)*100 -> 0
A25: Ventes dans la région | B25: 0 | C25: 0 | D25: =IF(C25=0,0,(B25-C25)/C25)*100 -> 0
A26: Ventes hors région | B26: 0 | C26: 0 | D26: =IF(C26=0,0,(B26-C26)/C26)*100 -> 0
A27: Ventes groupe | B27: 0 | C27: 0 | D27: =IF(C27=0,0,(B27-C27)/C27)*100 -> 0
A28: Ventes sur internet | B28: 0 | C28: 0 | D28: =IF(C28=0,0,(B28-C28)/C28)*100 -> 0
A29: TOTAL : VENTES DE TRAVAUX ET SERVICES VENDUS | B29: =SUM(B25:B28) -> 0 | C29: =SUM(C25:C28) -> 0 | D29: =IF(C29=0,0,(B29-C29)/C29)*100 -> 0
A31: Produits accessoires | B31: 0 | C31: 0 | D31: =IF(C31=0,0,(B31-C31)/C31)*100 -> 0
A33: TOTAL : CHIFFRES D'AFFAIRES | B33: =B17+B23+B29+B31 -> 0 | C33: =C17+C23+C29+C31 -> 0 | D33: =IF(C33=0,0,(B33-C33)/C33)*100 -> 0
D34: =IF(C34=0,0,(B34-C34)/C34)*100 -> 0
A35: Production immobilisée | D35: =IF(C35=0,0,(B35-C35)/C35)*100 -> 0
A36: Subventions d'exploitation | B36: 0 | C36: 0 | D36: =IF(C36=0,0,(B36-C36)/C36)*100 -> 0
A37: Autres produits | B37: 0 | C37: 0 | D37: =IF(C37=0,0,(B37-C37)/C37)*100 -> 0
A38: TOTAL : AUTRES PRODUITS | B38: 0 | C38: 0 | D38: =IF(C38=0,0,(B38-C38)/C38)*100 -> 0
A40: TOTAL | B40: =B33+B38 -> 0 | C40: =C33+C38 -> 0 | D40: =IF(C40=0,0,(B40-C40)/C40)*100 -> 0
A41: Commentaires:
A42: • Justifier toute variation significative.
A43: • Détailler, produits, intermédiaires, produits résiduels, produits accessoires, autres produits si significatifs.

Sheet NOTE 22
A5: =_soNom -> Cecotra | B5: =_ExerClos -> Exercice clos le 31/12/2025
A6: =_soId -> 3201810353457 | B6: =_Duree -> Durée (en mois) 12
A8: NOTE 22
A9: ACHATS
A10: Libellés | B10: =_ExerFin -> 31/12/2025 | C10: =_ExerFin1 -> 31/12/2024 | D10: Variation en %
A11: Achats dans la région | B11: 0 | C11: 0 | D11: =IF(C11=0,0,(B11-C11)/C11)*100 -> 0
A12: Achats hors région | B12: 0 | C12: 0 | D12: =IF(C12=0,0,(B12-C12)/C12)*100 -> 0
A13: Achats groupe | B13: 0 | C13: 0 | D13: =IF(C13=0,0,(B13-C13)/C13)*100 -> 0
A14: TOTAL : ACHATS DE MARCHANDISES | B14: =SUM(B11:B13) -> 0 | C14: =SUM(C11:C13) -> 0 | D14: =IF(C14=0,0,(B14-C14)/C14)*100 -> 0
A16: Achats dans la région | B16: 0 | C16: 0 | D16: =IF(C16=0,0,(B16-C16)/C16)*100 -> 0
A17: Achats hors région | B17: 0 | C17: 0 | D17: =IF(C17=0,0,(B17-C17)/C17)*100 -> 0
A18: Achats groupe | B18: 0 | C18: 0 | D18: =IF(C18=0,0,(B18-C18)/C18)*100 -> 0
A19: TOTAL : ACHATS MATIERES PREMIERES ET FOURNITURES LIEES | B19: =SUM(B15:B18) -> 0 | C19: =SUM(C15:C18) -> 0 | D19: =IF(C19=0,0,(B19-C19)/C19)*100 -> 0
A21: Matières consommables | B21: 0 | C21: 0 | D21: =IF(C21=0,0,(B21-C21)/C21)*100 -> 0
A22: Matières combustibles | B22: 0 | C22: 0 | D22: =IF(C22=0,0,(B22-C22)/C22)*100 -> 0
A23: Produits d'entretien | B23: 0 | C23: 0 | D23: =IF(C23=0,0,(B23-C23)/C23)*100 -> 0
A24: Fournitures d'atelier, d'usine et de magasin | B24: 0 | C24: 0 | D24: =IF(C24=0,0,(B24-C24)/C24)*100 -> 0
A25: Eau | B25: 0 | C25: 0 | D25: =IF(C25=0,0,(B25-C25)/C25)*100 -> 0
A26: Electricité | B26: 0 | C26: 0 | D26: =IF(C26=0,0,(B26-C26)/C26)*100 -> 0
A27: Autres énergies | B27: 0 | C27: 0 | D27: =IF(C27=0,0,(B27-C27)/C27)*100 -> 0
A28: Fourniture d'entretien | B28: 0 | C28: 0 | D28: =IF(C28=0,0,(B28-C28)/C28)*100 -> 0
A29: Fourniture de bureau | B29: 0 | C29: 0 | D29: =IF(C29=0,0,(B29-C29)/C29)*100 -> 0
A30: Petit matériel et outillages | B30: 0 | C30: 0 | D30: =IF(C30=0,0,(B30-C30)/C30)*100 -> 0
A31: Achats études, prestations de services, de travaux matériels et équipements | B31: 0 | C31: 0 | D31: =IF(C31=0,0,(B31-C31)/C31)*100 -> 0
A32: Achats d'emballages | B32: 0 | C32: 0 | D32: =IF(C32=0,0,(B32-C32)/C32)*100 -> 0
... A34: Remises rabais, remises et ristournes | B34: 0 | C34: 0 | D34: =IF(C34=0,0,(B34-C34)/C34)*100 -> 0
A35: TOTAL : AUTRES ACHATS | B35: =SUM(B20:B33) -> 0 | C35: =SUM(C20:C33) -> 0 | D35: =IF(C35=0,0,(B35-C35)/C35)*100 -> 0
A37: Commentaire :
A38:  Commenter toute variation significative.

Sheet NOTE 23
A4: =_soNom -> Cecotra | C4: =_ExerClos -> Exercice clos le 31/12/2025
A5: =_soId -> 3201810353457 | C5: =_Duree -> Durée (en mois) 12
A7: NOTE 23
A8: TRANSPORTS
A9: Libellés | B9: =_ExerFin -> 31/12/2025 | C9: =_ExerFin1 -> 31/12/2024 | D9: Variation en %
A10: Transports sur ventes | B10: 0 | C10: 0 | D10: =IF(C10=0,0,(B10-C10)/C10)*100 -> 0
A11: Transports pour le compte de tiers | B11: 0 | C11: 0 | D11: =IF(C11=0,0,(B11-C11)/C11)*100 -> 0
A12: Transport du personnel | B12: 0 | C12: 0 | D12: =IF(C12=0,0,(B12-C12)/C12)*100 -> 0
A13: Transports de plis | B13: 0 | C13: 0 | D13: =IF(C13=0,0,(B13-C13)/C13)*100 -> 0
A14: Autres transports | B14: 0 | C14: 0 | D14: =IF(C14=0,0,(B14-C14)/C14)*100 -> 0
A15: TOTAL | B15: =SUM(B10:B14) -> 0 | C15: =SUM(C10:C14) -> 0 | D15: =IF(C15=0,0,(B15-C15)/C15)*100 -> 0
A16: Commentaire :
A17:  Commenter toute variation significative.

Sheet NOTE 24
A4: =_soNom -> Cecotra | C4: =_ExerClos -> Exercice clos le 31/12/2025
A5: =_soId -> 3201810353457 | C5: =_Duree -> Durée (en mois) 12
A7: NOTE 24
A8: SERVICES EXTERIEURS
A9: Libellés | B9: =_ExerFin -> 31/12/2025 | C9: =_ExerFin1 -> 31/12/2024 | D9: Variation en %
A10: Sous-traitance générale | B10: 0 | C10: 0 | D10: =IF(C10=0,0,(B10-C10)/C10)*100 -> 0
A11: Locations et charges locatives | B11: 480000 | C11: 0 | D11: =IF(C11=0,0,(B11-C11)/C11)*100 -> 0
A12: Redevances de location acquisition | B12: 0 | C12: 0 | D12: =IF(C12=0,0,(B12-C12)/C12)*100 -> 0
A13: Entretien, réparations et maintenance | B13: 0 | C13: 0 | D13: =IF(C13=0,0,(B13-C13)/C13)*100 -> 0
A14: Primes d'assurance | B14: 0 | C14: 0 | D14: =IF(C14=0,0,(B14-C14)/C14)*100 -> 0
A15: Etudes, recherches et documentation | B15: 0 | C15: 0 | D15: =IF(C15=0,0,(B15-C15)/C15)*100 -> 0
A16: Publicité, publications, relations publiques | B16: 0 | C16: 0 | D16: =IF(C16=0,0,(B16-C16)/C16)*100 -> 0
A17: Frais de télécommunications | B17: 0 | C17: 0 | D17: =IF(C17=0,0,(B17-C17)/C17)*100 -> 0
A18: Frais bancaires | B18: 266886 | C18: 0 | D18: =IF(C18=0,0,(B18-C18)/C18)*100 -> 0
A19: Rémunérations d'intermédiaires et de conseils | B19: 0 | C19: 0 | D19: =IF(C19=0,0,(B19-C19)/C19)*100 -> 0
A20: Frais de formation du personnel | B20: 0 | C20: 0 | D20: =IF(C20=0,0,(B20-C20)/C20)*100 -> 0
A21: Redevances pour brevets, licences, logiciels, concession et droits similaires | B21: 0 | C21: 0 | D21: =IF(C21=0,0,(B21-C21)/C21)*100 -> 0
... A23: Autres charges externes | B23: 0 | C23: 0 | D23: =IF(C23=0,0,(B23-C23)/C23)*100 -> 0
A24: TOTAL | B24: =SUM(B10:B23) -> 746886 | C24: =SUM(C10:C23) -> 0 | D24: =IF(C24=0,0,(B24-C24)/C24)*100 -> 0
A25: Commentaire :
A26:  Commenter toute variation significative.

Sheet NOTE 25
A5: =_soNom -> Cecotra | C5: =_ExerClos -> Exercice clos le 31/12/2025
A6: =_soId -> 3201810353457 | C6: =_Duree -> Durée (en mois) 12
A8: NOTE 25
A9: IMPOTS ET TAXES
A10: Libellés | B10: =_ExerFin -> 31/12/2025 | C10: =_ExerFin1 -> 31/12/2024 | D10: Variation en %
A11: Impôts et taxes directs | B11: 124800 | C11: 0 | D11: =IF(C11=0,0,(B11-C11)/C11)*100 -> 0
A12: Impôts et taxes indirects | B12: 0 | C12: 0 | D12: =IF(C12=0,0,(B12-C12)/C12)*100 -> 0
A13: Droits d'enregistrement | B13: 0 | C13: 0 | D13: =IF(C13=0,0,(B13-C13)/C13)*100 -> 0
A14: Pénalités et amendes fiscales | B14: 0 | C14: 0 | D14: =IF(C14=0,0,(B14-C14)/C14)*100 -> 0
A15: Autres impôts et taxes | B15: 0 | C15: 0 | D15: =IF(C15=0,0,(B15-C15)/C15)*100 -> 0
A16: TOTAL | B16: =SUM(B11:B15) -> 124800 | C16: =SUM(C11:C15) -> 0 | D16: =IF(C16=0,0,(B16-C16)/C16)*100 -> 0
A17: Commentaires:
A18: • Commenter toute variation significative.
A19: • Détailler les pénalités et amendes et indiquer la cause.

Sheet NOTE 26
A4: =_soNom -> Cecotra | C4: =_ExerClos -> Exercice clos le 31/12/2025
A5: =_soId -> 3201810353457 | C5: =_Duree -> Durée (en mois) 12
A7: NOTE 26
A8: AUTRES CHARGES
A9: Libellés | B9: =_ExerFin -> 31/12/2025 | C9: =_ExerFin1 -> 31/12/2024 | D9: Variation en %
A10: Pertes sur créances clients | B10: 0 | C10: 0 | D10: =IF(C10=0,0,(B10-C10)/C10)*100 -> 0
A11: Pertes sur autres débiteurs | B11: 0 | C11: 0 | D11: =IF(C11=0,0,(B11-C11)/C11)*100 -> 0
A12: Quote-part de résultat sur opérations faites en commun | B12: 0 | C12: 0 | D12: =IF(C12=0,0,(B12-C12)/C12)*100 -> 0
A13: Valeur comptable des cessions courantes d'immobilisations | B13: 0 | C13: 0 | D13: =IF(C13=0,0,(B13-C13)/C13)*100 -> 0
A14: Indemnités de fonction et autres rémunérations d'administrateurs | B14: 0 | C14: 0 | D14: =IF(C14=0,0,(B14-C14)/C14)*100 -> 0
A15: Dons et mécénat | B15: 0 | C15: 0 | D15: =IF(C15=0,0,(B15-C15)/C15)*100 -> 0
A16: Autres charges diverses | B16: 0 | C16: 0 | D16: =IF(C16=0,0,(B16-C16)/C16)*100 -> 0
A17: Charges pour provisions et provisions pour risques à court terme d'exploitation (voir note 28) | B17: 0 | C17: 0 | D17: =IF(C17=0,0,(B17-C17)/C17)*100 -> 0
A19: TOTAL | B19: =SUM(B10:B18) -> 0 | C19: =SUM(C10:C18) -> 0 | D19: =IF(C19=0,0,(B19-C19)/C19)*100 -> 0
A20: Commentaires :
A21: • Commenter toute variation significative.
A22: • Indiquer la date du PV de l'AGO ou du CA qui fixe les rémunérations des administrateurs.
A23: • Indiquer les organismes bénéficiaires des dons.

Sheet NOTE 27A
A5: =_soNom -> Cecotra | C5: =_ExerClos -> Exercice clos le 31/12/2025
A6: =_soId -> 3201810353457 | C6: =_Duree -> Durée (en mois) 12
A8: NOTE 27A
A9: CHARGES DE PERSONNEL
A10: Libellés | B10: =_ExerFin -> 31/12/2025 | C10: =_ExerFin1 -> 31/12/2024 | D10: Variation en %
A11: Rémunérations directes versées au personnel | B11: 3120000 | C11: 0 | D11: =IF(C11=0,0,(B11-C11)/C11)*100 -> 0
A12: Indemnités forfaitaires versées au personnel | B12: 0 | C12: 0 | D12: =IF(C12=0,0,(B12-C12)/C12)*100 -> 0
A13: Charges sociales | B13: 592800 | C13: 0 | D13: =IF(C13=0,0,(B13-C13)/C13)*100 -> 0
A14: Rémunérations et charges sociales de l'exploitant individuel | B14: 0 | C14: 0 | D14: =IF(C14=0,0,(B14-C14)/C14)*100 -> 0
A15: Rémunération transférée de personnel extérieur | B15: 0 | C15: 0 | D15: =IF(C15=0,0,(B15-C15)/C15)*100 -> 0
A16: Autres charges sociales | B16: 0 | C16: 0 | D16: =IF(C16=0,0,(B16-C16)/C16)*100 -> 0
A18: TOTAL | B18: =SUM(B11:B17) -> 3712800 | C18: =SUM(C11:C17) -> 0 | D18: =IF(C18=0,0,(B18-C18)/C18)*100 -> 0
A19: Commentaires :
A20: • Commenter toute variation significative.
A21: • Indiquer la nature et la durée du contrat du personnel extérieur.

Sheet NOTE 27B
A3: =_soNom -> Cecotra | L3: =_ExerClos -> Exercice clos le 31/12/2025
A4: =_soId -> 3201810353457 | L4: =_Duree -> Durée (en mois) 12
A5: NOTE 27B
A6: EFFECTIFS, MASSE SALARIALE ET PERSONNEL EXTERIEUR
B7: EFFECTIF ET MASSE SALARIALE | C7: EFFECTIFS | J7: MASSE SALARIALE
C10: Nationaux | E10: Autres Etats de l’OHADA | G10: Hors OHADA | I10: TOTAL | J10: Nationaux | L10: Autres Etats de l’OHADA | N10: Hors OHADA | P10: TOTAL
B11: QUALIFICATIONS | C11: M | D11: F | E11: M | F11: F | G11: M | H11: F | J11: M | K11: F | L11: M | M11: F | N11: M | O11: F
A12: YA | B12: 1. Cadres supérieurs | I12: =SUM(C12:H12) -> 0 | P12: =SUM(J12:O12) -> 0
A13: YB | B13: 2. Techniciens supérieurs et cadres moyens | I13: =SUM(C13:H13) -> 0 | P13: =SUM(J13:O13) -> 0
A14: YC | B14: 3. Techniciens, agents de maîtrise et ouvriers qualifiés | I14: =SUM(C14:H14) -> 0 | P14: =SUM(J14:O14) -> 0
A15: YD | B15: 4. Employés, manœuvres, ouvriers et apprentis | I15: =SUM(C15:H15) -> 0 | P15: =SUM(J15:O15) -> 0
A16: YE | B16: TOTAL (1) | C16: =SUM(C12:C15) -> 0 | D16: =SUM(D12:D15) -> 0 | E16: =SUM(E12:E15) -> 0 | F16: =SUM(F12:F15) -> 0 | G16: =SUM(G12:G15) -> 0 | H16: =SUM(H12:H15) -> 0 | I16: =SUM(I12:I15) -> 0 | J16: =SUM(J12:J15) -> 0 | ... P16: =SUM(P12:P15) -> 0
A18: YF | B18: Permanents | C18: =C16 -> 0 | D18: =D16 -> 0 | E18: =E16 -> 0 | F18: =F16 -> 0 | G18: =G16 -> 0 | H18: =H16 -> 0 | I18: =I16 -> 0 | J18: =J16 -> 0 | ... P18: =P16 -> 0
A19: YG | B19: Saisonniers
J21: Facturation à l’entité
B22: 2. Personnel extérieur
A23: YH | B23: 1. Cadres supérieurs | K23: 0
A24: YI | B24: 2. Techniciens supérieurs et cadres moyens | K24: 0
A25: YJ | B25: 3. Techniciens, agents de maîtrise et ouvriers qualifiés | K25: 0
A26: YK | B26: 4. Employés, manœuvres, ouvriers et apprentis | N26: M : Masculin
A27: YL | B27: TOTAL (2) | D27: =SUM(D23:D26) -> 0 | E27: =SUM(E23:E26) -> 0 | F27: =SUM(F23:F26) -> 0 | G27: =SUM(G23:G26) -> 0 | H27: =SUM(H23:H26) -> 0 | I27: =SUM(I23:I26) -> 0 | J27: =SUM(J23:J26) -> 0 | K27: =SUM(K23:K26) -> 0
A29: YM | B29: Permanents
A30: YN | B30: Saisonniers
A32: YO | B32: TOTAL (1 + 2) | C32: =C16+C27 -> 0 | D32: =D16+D27 -> 0 | E32: =E16+E27 -> 0 | F32: =F16+F27 -> 0 | G32: =G16+G27 -> 0 | H32: =H16+H27 -> 0 | I32: =I16+I27 -> 0
A34: Commentaire :
A35: · Faire un commentaire si nécessaire en cas de mouvement significatif du personnel.

Sheet NOTE 28
A4: =_soNom -> Cecotra | F4: =_ExerClos -> Exercice clos le 31/12/2025
A5: =_soId -> 3201810353457 | F5: =_Duree -> Durée (en mois) 12
A7: NOTE 28
A8: PROVISIONS ET DEPRECIATIONS INSCRITES AU BILAN
A9: RUBRIQUE | B9: A | C9: B | F9: C | I9: D = A + B - C
B10: PROVISIONS A LOUVERTURE DE L’EXERCICE | C10: AUGMENTATIONS DOTATIONS | F10: DIMINUTIONS REPRISES | I10: PROVISIONS LA CLOTURE DE L’EXERCICE
C11: D’EXPLOITATION | D11: FINANCIERES | E11: HORS ACTIVITES ORDINAIRES | F11: D’EXPLOITATION | G11: FINANCIERES | H11: HORS ACTIVITES ORDINQIRES
A12: 1. Provisions réglementées | B12: 0 | C12: 0 | D12: 0 | E12: 0 | F12: 0 | G12: 0 | H12: 0 | I12: =B12+C12+D12+E12-F12-G12-H12 -> 0
A13: 2. Provisions financières pour risques et charges | B13: 0 | C13: 0 | D13: 0 | E13: 0 | F13: 0 | G13: 0 | H13: 0 | I13: =B13+C13+D13+E13-F13-G13-H13 -> 0
A14: 3. Dépréciation des immobilisations | B14: 0 | C14: 0 | D14: 0 | E14: 0 | F14: 0 | G14: 0 | H14: 0 | I14: =B14+C14+D14+E14-F14-G14-H14 -> 0
A15: TOTAL DOTATIONS | B15: =SUM(B12:B14) -> 0 | C15: =SUM(C12:C14) -> 0 | D15: =SUM(D12:D14) -> 0 | E15: =SUM(E12:E14) -> 0 | F15: =SUM(F12:F14) -> 0 | G15: =SUM(G12:G14) -> 0 | H15: =SUM(H12:H14) -> 0 | I15: =B15+C15+D15+E15-F15-G15-H15 -> 0
A17: 4. Dépréciations des stocks | B17: 0 | C17: 0 | D17: 0 | E17: 0 | F17: 0 | G17: 0 | H17: 0 | I17: =B17+C17-F17 -> 0
A18: 5. Dépréciations actif circulant HAO | B18: 0 | C18: 0 | D18: 0 | E18: 0 | F18: 0 | G18: 0 | H18: 0 | I18: =B18+C18-F18 -> 0
A19: 6. Dépréciations fournisseurs | B19: 0 | C19: 0 | D19: 0 | E19: 0 | F19: 0 | G19: 0 | H19: 0 | I19: =B19+C19-F19 -> 0
A20: 7. Dépréciations clients | B20: 0 | C20: 0 | D20: 0 | E20: 0 | F20: 0 | G20: 0 | H20: 0 | I20: =B20+C20-F20 -> 0
A21: 5. Dépréciations fournisseurs | B21: 0 | C21: 0 | D21: 0 | E21: 0 | F21: 0 | G21: 0 | H21: 0 | I21: =B21+C21-F21 -> 0
A22: 7. Dépréciations autres créances | B22: 0 | C22: 0 | D22: 0 | E22: 0 | F22: 0 | G22: 0 | H22: 0 | I22: =B22+C22+D22+E22-F22-G22-H22 -> 0
A23: 8. Dépréciations titres de placement | B23: 0 | C23: 0 | D23: 0 | E23: 0 | F23: 0 | G23: 0 | H23: 0
A24: 9. Dépréciations valeurs à encaisser | B24: 0 | C24: 0 | D24: 0 | E24: 0 | F24: 0 | G24: 0 | H24: 0
A25: 10. Dépréciations disponibilité | B25: 0 | C25: 0 | D25: 0 | E25: 0 | F25: 0 | G25: 0 | H25: 0
A26: 11. Dépréciations et provisions pour risques d’exploitation à court terme | B26: 0 | C26: 0 | D26: 0 | E26: 0 | F26: 0 | G26: 0 | H26: 0
A27: 12. Dépréciations et provisions pour risques financiers à court terme
A28: TOTAL CHARGES POUR DEPRECIATIONS ET PROVISIONS A COURT TERME | B28: =SUM(B17:B27) -> 0 | C28: =SUM(C17:C27) -> 0 | D28: =SUM(D17:D27) -> 0 | E28: =SUM(E17:E27) -> 0 | F28: =SUM(F17:F27) -> 0 | G28: =SUM(G17:G27) -> 0 | H28: =SUM(H17:H27) -> 0 | I28: =SUM(I17:I27) -> 0
A30: TOTAL PROVISIONS ET DEPRECIATIONS | B30: =B15+B28 -> 0 | C30: =C15+C28 -> 0 | D30: =D15+D28 -> 0 | E30: =E15+E28 -> 0 | F30: =F15+F28 -> 0 | G30: =G15+G28 -> 0 | H30: =H15+H28 -> 0 | I30: =I15+I28 -> 0
A32: Commentaire :
A33: Indiquer les événements et circonstances qui ont conduit à la constitution et à la reprise de la dépréciation et de la provision.

Sheet NOTE 29
A4: =_soNom -> Cecotra | C4: =_ExerClos -> Exercice clos le 31/12/2025
A5: =_soId -> 3201810353457 | C5: =_Duree -> Durée (en mois) 12
A7: NOTE 29
A8: CHARGES ET REVENUS FINANCIERS
A9: Libellés | B9: =_ExerFin -> 31/12/2025 | C9: =_ExerFin1 -> 31/12/2024 | D9: Variation en %
A10: Intérêts des emprunts | B10: 0 | C10: 0 | D10: =IF(C10=0,0,(B10-C10)/C10)*100 -> 0
A11: Intérêts dans loyers de locations acquisition | B11: 0 | C11: 0 | D11: =IF(C11=0,0,(B11-C11)/C11)*100 -> 0
A12: Escomptes accordés | B12: 0 | C12: 0 | D12: =IF(C12=0,0,(B12-C12)/C12)*100 -> 0
A13: Autres intérêts | B13: 0 | C13: 0 | D13: =IF(C13=0,0,(B13-C13)/C13)*100 -> 0
A14: Escomptes des effets de commerce | B14: 0 | C14: 0 | D14: =IF(C14=0,0,(B14-C14)/C14)*100 -> 0
A15: Pertes de change | B15: 0 | C15: 0 | D15: =IF(C15=0,0,(B15-C15)/C15)*100 -> 0
A16: Pertes sur cessions de titres de placement | B16: 0 | C16: 0 | D16: =IF(C16=0,0,(B16-C16)/C16)*100 -> 0
A17: Malis provenant d’attribution gratuite d’actions au personnel salarié et aux dirigeants | B17: 0 | C17: 0 | D17: =IF(C17=0,0,(B17-C17)/C17)*100 -> 0
A18: Pertes sur risques financiers | B18: 0 | C18: 0 | D18: =IF(C18=0,0,(B18-C18)/C18)*100 -> 0
A19: Charges pour dépréciation et provisions à court terme à caractère financier (voir note 28) | B19: 0 | C19: 0 | D19: =IF(C19=0,0,(B19-C19)/C19)*100 -> 0
A20: SOUS TOTAL : FRAIS FINANCIERS | B20: =SUM(B10:B19) -> 0 | C20: =SUM(C10:C19) -> 0 | D20: =IF(C20=0,0,(B20-C20)/C20)*100 -> 0
A22: Intérêts de prêts et créances diverses | B22: 0 | C22: 0 | D22: =IF(C22=0,0,(B22-C22)/C22)*100 -> 0
A23: Revenus de participations | B23: 0 | C23: 0 | D23: =IF(C23=0,0,(B23-C23)/C23)*100 -> 0
A24: Escomptes obtenus | B24: 0 | C24: 0 | D24: =IF(C24=0,0,(B24-C24)/C24)*100 -> 0
A25: Revenus de placement | B25: 0 | C25: 0 | D25: =IF(C25=0,0,(B25-C25)/C25)*100 -> 0
A26: Intérêts dans loyers de locations financement | B26: 0 | C26: 0 | D26: =IF(C26=0,0,(B26-C26)/C26)*100 -> 0
A27: Gains de change | B27: 0 | C27: 0 | D27: =IF(C27=0,0,(B27-C27)/C27)*100 -> 0
A28: Gains sur cessions de titres de placement | B28: 0 | C28: 0 | D28: =IF(C28=0,0,(B28-C28)/C28)*100 -> 0
A29: Gains sur risques financiers | B29: 0 | C29: 0 | D29: =IF(C29=0,0,(B29-C29)/C29)*100 -> 0
A30: Reprises de charges pour dépréciation et provisions à court terme à caractère financier (voir note 28) | B30: 0 | C30: 0 | D30: =IF(C30=0,0,(B30-C30)/C30)*100 -> 0
A31: SOUS TOTAL : REVENUS FINANCIERS | B31: =SUM(B22:B30) -> 0 | C31: =SUM(C22:C30) -> 0 | D31: =IF(C31=0,0,(B31-C31)/C31)*100 -> 0
A33: TOTAL | B33: =B20+B31 -> 0 | C33: =C20+C31 -> 0 | D33: =IF(C33=0,0,(B33-C33)/C33)*100 -> 0
A34: Commentaires :
A35: • Commenter toute variation significative
A36: • En cas de paiement à terme, indiquer le montant des intérêts non comptabilisés

Sheet NOTE 30
A4: =_soNom -> Cecotra | C4: =_ExerClos -> Exercice clos le 31/12/2025
A5: =_soId -> 3201810353457 | C5: =_Duree -> Durée (en mois) 12
A7: NOTE 30
A8: AUTRES CHARGES ET PRODUITS HAO
A9: Libellés | B9: =_ExerFin -> 31/12/2025 | C9: =_ExerFin1 -> 31/12/2024 | D9: Variation en %
A10: Charges HAO constatées (1) à détailler | B10: 0 | C10: 0 | D10: =IF(C10=0,0,(B10-C10)/C10)*100 -> 0
A11: Pertes sur créances HAO | B11: 0 | C11: 0 | D11: =IF(C11=0,0,(B11-C11)/C11)*100 -> 0
A12: Dons et libéralités accordés | B12: 0 | C12: 0 | D12: =IF(C12=0,0,(B12-C12)/C12)*100 -> 0
A13: Abandons de créances consentis | B13: 0 | C13: 0 | D13: =IF(C13=0,0,(B13-C13)/C13)*100 -> 0
A14: Charges provisionnées HAO | B14: 0 | C14: 0 | D14: =IF(C14=0,0,(B14-C14)/C14)*100 -> 0
A15: Dotations hors activités ordinaires | B15: 0 | C15: 0 | D15: =IF(C15=0,0,(B15-C15)/C15)*100 -> 0
A16: Participation des travailleurs | B16: 0 | C16: 0 | D16: =IF(C16=0,0,(B16-C16)/C16)*100 -> 0
A17: Subventions d'équilibre | B17: 0 | C17: 0 | D17: =IF(C17=0,0,(B17-C17)/C17)*100 -> 0
A18: SOUS TOTAL : AUTRES CHARGES HAO | B18: =RESULTAT!E46 -> 0 | C18: =RESULTAT!F46 -> 0 | D18: =IF(C18=0,0,(B18-C18)/C18)*100 -> 0
A20: Produits HAO constatés (1) à détailler | B20: 0 | C20: 0 | D20: =IF(C20=0,0,(B20-C20)/C20)*100 -> 0
A21: Dons et libéralités obtenus | B21: 0 | C21: 0 | D21: =IF(C21=0,0,(B21-C21)/C21)*100 -> 0
A22: Abandons de créances obtenus | B22: 0 | C22: 0 | D22: =IF(C22=0,0,(B22-C22)/C22)*100 -> 0
A23: Transferts de charges HAO | B23: 0 | C23: 0 | D23: =IF(C23=0,0,(B23-C23)/C23)*100 -> 0
A24: Reprises des charges pour dépréciations et provisions à court terme HAO | B24: 0 | C24: 0 | D24: =IF(C24=0,0,(B24-C24)/C24)*100 -> 0
A25: Reprises hors activités ordinaires | B25: 0 | C25: 0 | D25: =IF(C25=0,0,(B25-C25)/C25)*100 -> 0
A26: SOUS TOTAL : AUTRES PRODUITS HAO | B26: =RESULTAT!E44 -> 0 | C26: =RESULTAT!F44 -> 0 | D26: =IF(C26=0,0,(B26-C26)/C26)*100 -> 0
A28: TOTAL | B28: =+B18+B26 -> 0 | C28: =+C18+C26 -> 0 | D28: =IF(C28=0,0,(B28-C28)/C28)*100 -> 0
A29: Commentaire :
A30:  Commenter toute variation significative.

Sheet NOTE 31
A4: =_soNom -> Cecotra | D4: =_ExerClos -> Exercice clos le 31/12/2025
A5: =_soId -> 3201810353457 | D5: =_Duree -> Durée (en mois) 12
A6: NOTE 31
A7: REPARATION DU RESULTAT ET AUTRES ELEMENTS CARACTERISTIQUES DES CINQ DERNIERS EXERCICES
A8: EXERCICES CONCERNES (1) | B8: N | C8: N-1 | D8: N-2 | E8: N-3 | F8: N-4
A10: STRUCTURE DU CAPITAL A LA CLOTURE DE L’EXERCICE(2) | B10: =B11 -> 0 | C10: =C11 -> 0 | D10: =D11 -> 0 | E10: =E11 -> 0 | F10: =F11 -> 0
A11: Capital social
A12: Actions ordinaires
A13: Actions à dividendes prioritaires (A.D.P) sans droit de vote
A14: Actions nouvelles à mettre :
A15: - Par conversion d’obligations
A16: - Par exercice de droits de souscription
A17: OPERATION ET RESULTATS DE L’EXERCICE (3)
A18: Chiffres d’affaire hors taxes | B18: 983417641 | C18: =RESULTAT!F16 -> 105559492
A19: Résultats des activités ordinaires (R.A.O) hors dotation et reprises (exploitation et financières) | B19: 22872214 | C19: =RESULTAT!F35+RESULTAT!F34 -> 2167142
A20: Participation des travailleurs aux bénéfices | B20: 0
A21: Impôt sur le résultat | B21: 6861600 | C21: =RESULTAT!F49 -> 1055590
A22: Résultat net(4) | B22: 16010614 | C22: =RESULTAT!F50 -> 418023
A23: RESULTAT ET DIVIDENDE DISTRIBUES
A24: Résultat distribué (5)
A25: Dividende attribué à chaque action
A26: PERSONNEL ET POLITIQUE SALARIALE
A27: Effectif moyen des travailleurs au cours de l’exercice (6)
A28: Effectif moyen de personnel extérieur
A29: Masse salariale distribuée au cours de l’exercice (7) | B29: 3120000
A30: Avantages sociaux versés au cours de l’exercice (8) [Sécurité sociale, œuvres sociales] | B30: 592800
A31: Personnel extérieur facturé à l’entité (9) | B31: 0
A33: (1) Y compris l’exercice dont les états financiers sont soumis à l’approbation de l’Assemblée | B33: (6) Personnel propre
A34: (2) Indication, en cas de libération partielle du capital, du montant du capital non appelé | B34: (7) Total des comptes 661, 662, 663
A35: (3) Les éléments de cette rubrique sont ceux figurant au compte de résultat | B35: (8) Total des comptes 664,668
A36: (4) Le résultat, lorsqu’il est négatif, doit être mis entre parenthèses | B36: (9) Compte 667
A37: (5) L’exercice N correspond au dividende proposé du dernier exercice

Sheet NOTE 32
A4: =_soNom -> Cecotra | K4: =_ExerClos -> Exercice clos le 31/12/2025
A5: =_soId -> 3201810353457 | K5: =_Duree -> Durée (en mois) 12
A6: NOTE 32
A7: PRODUCTION DE L’EXERCICE
A9: DESIGNATION DU PRODUIT | B9: UNITE DE QUANTITE CHOISIE | C9: PRODUCTION VENDUE DANS LE PAYS | E9: PRODUCTION VENDUE DANS LES AUTRES PAYS DE L’OHADA | G9: PRODUCTION VENDUE HORS OHADA | I9: PRODUCTION IMMOBILISEE | K9: STOCK OUVERTURE DE L’EXERCICE | M9: STOCK CLOTURE DE L’EXERCICE
C11: Quantité | D11: Valeur | E11: Quantité | F11: Valeur | G11: Quantité | H11: Valeur | I11: Quantité | J11: Valeur | K11: Quantité | L11: Valeur | M11: Quantité | N11: Valeur
A20: NON VENTILE
A22: TOTAL

Sheet NOTE 33
A4: =_soNom -> Cecotra | F4: =_ExerClos -> Exercice clos le 31/12/2025
A5: =_soId -> 3201810353457 | F5: =_Duree -> Durée (en mois) 12
A6: NOTE 33
A7: ACHATS DESTINES A LA PRODUCTION
A9: DESIGNATION DES MATIERES ET PRODUITS | B9: UNITE DE QUANTITE CHOISIE | C9: ACHATS EFFECTUES AU COURS DE L’EXERCICE
C10: PRODUITS DE L’ETAT | E10: PRODUITS IMPORTES | I10: VARIATION DES STOCKS
E11: ACHETES DANS L’ETAT | G11: ACHETES HORS DE L’ETAT
C12: Quantité | D12: Valeur | E12: Quantité | F12: Valeur | G12: Quantité | H12: Valeur | I12: (en valeur)
A22: NON VENTILES
A24: TOTAL

Sheet NOTE 34
B1: NOTE 34 : FICHE DE SYNTHESE DES PRINCIPAUX INDICATEURS FINANCIERS
A2: =_soNom -> Cecotra | C2: =_ExerClos -> Exercice clos le 31/12/2025
A3: =_soId -> 3201810353457 | C3: =_Duree -> Durée (en mois) 12
A4: NOTE 34
A5: SYNTHESE DES PRINCIPAUX INDICATEURS FINANCIERS
A6: ( EN MILLIERS DE FRANCS) | C6: =_ExerFin -> 31/12/2025 | D6: =_ExerFin1 -> 31/12/2024 | E6: Variation en %
A8: ANALYSE DE L'ACTIVITE
A9: SOLDES INTERMEDIAIRES DE GESTION
A10: CHIFFRE D'AFFAIRES | C10: =RESULTAT!E16 -> 983417641 | D10: =RESULTAT!F16 -> 105559492 | E10: =IF(D10=0,0,(C10-D10)/D10)*100 -> 831.62408
A11: MARGE COMMERCIALE | C11: =RESULTAT!E12 -> 27456700 | D11: =RESULTAT!F12 -> 6706242 | E11: =IF(D11=0,0,(C11-D11)/D11)*100 -> 309.42006
A12: VALEUR AJOUTEE | C12: =RESULTAT!E30 -> 26585014 | D12: =RESULTAT!F30 -> 5879942 | E12: =IF(D12=0,0,(C12-D12)/D12)*100 -> 352.13055
A13: EXCEDENT BRUT D'EXPLOITATION (EBE) | C13: =RESULTAT!E32 -> 22872214 | D13: =RESULTAT!F32 -> 2167142 | E13: =IF(D13=0,0,(C13-D13)/D13)*100 -> 955.40911
A14: RESULTAT D'EXPLOITATION | C14: =RESULTAT!E35 -> 22872214 | D14: =RESULTAT!F35 -> 1473613 | E14: =IF(D14=0,0,(C14-D14)/D14)*100 -> 1452.1181
A15: RESULTAT FINANCIER | C15: =RESULTAT!E41 -> 0 | D15: =RESULTAT!F41 -> 0 | E15: =IF(D15=0,0,(C15-D15)/D15)*100 -> 0
A16: RESULTAT DES ACTIVITES ORDINAIRES | C16: =RESULTAT!E42 -> 22872214 | D16: =RESULTAT!F42 -> 1473613 | E16: =IF(D16=0,0,(C16-D16)/D16)*100 -> 1452.1181
A17: RESULTAT HORS ACTIVITES ORDINAIRES | C17: =RESULTAT!E47 -> 0 | D17: =RESULTAT!F47 -> 0 | E17: =IF(D17=0,0,(C17-D17)/D17)*100 -> 0
A18: RESULTAT NET | C18: =RESULTAT!E50 -> 16010614 | D18: =RESULTAT!F50 -> 418023 | E18: =IF(D18=0,0,(C18-D18)/D18)*100 -> 3730.0797
A19: DETERMINATION DE LA CAPACITE D'AUTOFINANCEMENT | E19: =IF(D19=0,0,(C19-D19)/D19)*100 -> 0
A20: EBE | C20: =C13 -> 22872214 | D20: =D13 -> 2167142
A21: + Valeurs comptables des cessions courantes d’immobilisation (compte 654) | C21: 0 | D21: 0
A22: - Produits des cessions courantes d’immobilisation (compte 754) | C22: 0 | D22: 0
A23: = CAPACITE D'AUTOFINANCEMENT D'EXPLOITATION | C23: =C20+C21-C22 -> 22872214 | D23: =D20+D21-D22 -> 2167142
A24: + Revenus financiers | C24: =RESULTAT!E36 -> 0 | D24: =RESULTAT!F36 -> 0
A25: + Gains de change | C25: 0 | D25: 0 | E25: 0 | F25: 0
A26: + Transferts de charges financières | C26: =RESULTAT!E38 -> 0 | D26: 0
A27: + Produits HAO | C27: =RESULTAT!E44 -> 0
A28: + Transferts de charges HAO | C28: 0 | D28: 0 | E28: 0 | F28: 0
A29: - Frais financiers | C29: =RESULTAT!E39 -> 0 | D29: =RESULTAT!F39 -> 0
A30: - Pertes de change | C30: 0 | D30: 0 | F30: 0
A31: - Participation | C31: =RESULTAT!E48 -> 0 | D31: 0
A32: - Impôts sur les résultats | C32: =RESULTAT!E49 -> 6861600 | D32: =RESULTAT!F49 -> 1055590
A33: = CAPACITE D'AUTOFINANCEMENT GLOBALE (C.A.F.G.) | C33: =TFT!H14 -> 16010614 | D33: =TFT!I14 -> 1531924 | E33: =IF(D33=0,0,(C33-D33)/D33)*100 -> 945.13109
A34: - Distributions de dividendes opérées durant l'exercice | C34: =TFT!H32 -> 0 | D34: =TFT!I32 -> 0 | E34: =IF(D34=0,0,(C34-D34)/D34)*100 -> 0
A35: = AUTOFINANCEMENT | C35: =C33-C34 -> 16010614 | D35: =D33-D34 -> 1531924 | E35: =IF(D35=0,0,(C35-D35)/D35)*100 -> 945.13109
A36: ANALYSE DE LA RENTABILITE
A37: Rentabilité économique = Résultat d’exploitation (a) /Capitaux propres + dettes financières | C37: =IF((PASSIF!D22+PASSIF!D23)=0,0,(RESULTAT!E32/(PASSIF!D22+PASSIF!D23))) -> 0.48318716 | D37: =IF(PASSIF!E22+PASSIF!E23=0,0,RESULTAT!F32/(PASSIF!E22+PASSIF!E23)) -> 0.069181349 | E37: =IF(D37=0,0,(C37-D37)/D37)*100 -> 598.43559
A38: Rentabilité financière = Résultat net/Capitaux propres | C38: =IF(PASSIF!D22=0,0,RESULTAT!E50/PASSIF!D22) -> 0.33823237 | D38: =IF(PASSIF!E22=0,0,RESULTAT!F50/PASSIF!E22) -> 0.013344485 | E38: =IF(D38=0,0,(C38-D38)/D38)*100 -> 2434.6228
A39: ANALYSE DE LA STRUCTURE FINANCIERE
A40: Capitaux propres et ressources assimilées | C40: =PASSIF!D22 -> 47336138 | D40: =PASSIF!E22 -> 31325524 | E40: =IF(D40=0,0,(C40-D40)/D40)*100 -> 51.110443
A41: + Dettes financières* et autres ressources assimilées (b) | C41: =PASSIF!D26 -> 0 | D41: =PASSIF!E26 -> 0 | E41: =IF(D41=0,0,(C41-D41)/D41)*100 -> 0
A42: = Ressources stables | C42: =C40+C41 -> 47336138 | D42: =D40+D41 -> 31325524 | E42: =IF(D42=0,0,(C42-D42)/D42)*100 -> 51.110443
A43: - Actif immobilisé (b) | C43: =ACTIF!F27 -> 3367095 | D43: =ACTIF!G27 -> 3367095 | E43: =IF(D43=0,0,(C43-D43)/D43)*100 -> 0
A44: = FONDS DE ROULEMENT (1) | C44: =C42-C43 -> 43969043 | D44: =D42-D43 -> 27958429 | E44: =IF(D44=0,0,(C44-D44)/D44) -> 0.57265786
A45: Actif circulant d'exploitation (b) | C45: =ACTIF!F29+ACTIF!F30 -> 75487514 | D45: =ACTIF!G29+ACTIF!G30 -> 52776486 | E45: =IF(D45=0,0,(C45-D45)/D45)*100 -> 43.032475
A46: - Passif circulant d'exploitation (b) | C46: =PASSIF!D34-PASSIF!D28 -> 31643607 | D46: =PASSIF!E34-PASSIF!E28 -> 24782007 | E46: =IF(D46=0,0,(C46-D46)/D46)*100 -> 27.68783
A47: = BESOIN DE FINANCEMENT D'EXPLOITATION (2) | C47: =C45-C46 -> 43843907 | D47: =D45-D46 -> 27994479 | E47: =IF(D47=0,0,(C47-D47)/D47)*100 -> 56.616264
A48: Actif circulant HAO (b) | C48: =ACTIF!F28 -> 0 | D48: =ACTIF!G28 -> 0 | E48: =IF(D48=0,0,(C48-D48)/D48)*100 -> 0
A49: - Passif circulant HAO (b) | C49: =PASSIF!D28 -> 0 | D49: =PASSIF!E28 -> 0 | E49: =IF(D49=0,0,(C49-D49)/D49)*100 -> 0
A50: = BESOIN DE FINANCEMENT HAO (3) | C50: =C48-C49 -> 0 | D50: =D48-D49 -> 0 | E50: =IF(D50=0,0,(C50-D50)/D50)*100 -> 0
A51: BESOIN DE FINANCEMENT GLOBAL (4) = (2) + (3) | C51: =C47+C50 -> 43843907 | D51: =D47+D50 -> 27994479 | E51: =IF(D51=0,0,(C51-D51)/D51)*100 -> 56.616264
E52: =IF(D52=0,0,(C52-D52)/D52)*100 -> 0
A53: TRESORERIE NETTE (5) = (1) - (4) | C53: =C44-C51 -> 125136 | D53: =D44-D51 -> -36050 | E53: =IF(D53=0,0,(C53-D53)/D53)*100 -> -447.11789
A54: CONTRÔLE : TRESORERIE NETTE = (TRESORERIE - ACTIF) - (TRESORERIE - PASSIF) | C54: =ACTIF!F38-PASSIF!D37 -> 125136 | D54: =ACTIF!G38-PASSIF!E37 -> -36050 | E54: =IF(D54=0,0,(C54-D54)/D54)*100 -> -447.11789
A55: ANALYSE DE LA VARIATION DE LA TRESORERIE
A56: Flux de trésorerie des activités opérationnelles | C56: =TFT!H20 -> 161186 | D56: =TFT!I20 -> -144039 | E56: =IF(D56=0,0,(C56-D56)/D56)*100 -> -211.90441
A57: -Flux de trésorerie des activités d'investissement | C57: =TFT!H27 -> 0 | D57: =TFT!I27 -> 0 | E57: =IF(D57=0,0,(C57-D57)/D57)*100 -> 0
A58: +Flux de trésorerie des activités de financement | C58: =TFT!H39 -> 0 | D58: =TFT!I39 -> 0 | E58: =IF(D58=0,0,(C58-D58)/D58)*100 -> 0
A59: = VARIATION DE LA TRESORERIE NETTE DE LA PERIODE | C59: =C56+C57+C58 -> 161186 | D59: =D56+D57+D58 -> -144039 | E59: =IF(D59=0,0,(C59-D59)/D59)*100 -> -211.90441
A60: ANALYSE DE LA VARIATION DE L’ENDETTEMENT FINANCIER NET
A61: Endettement financiers brut (Dettes financières* + Trésorerie-Passif) | C61: =PASSIF!D26+PASSIF!D37 -> 0 | D61: =PASSIF!E26+PASSIF!E37 -> 36050 | E61: =IF(D61=0,0,(C61-D61)/D61)*100 -> -100
A62: - Trésorerie-Actif | C62: =ACTIF!F38 -> 125136 | D62: =ACTIF!G38 -> 0 | E62: =IF(D62=0,0,(C62-D62)/D62)*100 -> 0
A63: = ENDETTEMENT NET | C63: =C61-C62 -> -125136 | D63: =D61-D62 -> 36050 | E63: =IF(D63=0,0,(C63-D63)/D63)*100 -> -447.11789
A64: (a) Résultat d’exploitation après impôt théorique sur le bénéfice.
A65: (b) Les écarts de conversion doivent être éliminés afin de ramener les créances et les dettes concernées à leur valeur initiale.
A66: Dettes financières* = emprunts et dettes financières diverses + dettes de location acquisition.

Sheet NOTE 35
A2: NOTE 35 : LISTE DES INFORMATIONS SOCIALES, ENVIRONNEMENTALES ET
A4: =_soNom -> Cecotra
A5: =_soId -> 3201810353457
A6: Note obligatoire pour les entités ayant un effectif de plus de 250 salariés
A7: Liste des informations sociales, environnementales et sociétales à fournir
A8: INFORMATIONS SOCIALES
A9: Emploi :
A10: • l'effectif total et la répartition des salariés par sexe, âge et zone géographique ;
A11: • les embauches et les licenciements ;
A12: • les rémunérations et leur évolution.
A13: Relations sociales :
A14: • l'organisation du dialogue social ;
A15: • le bilan des accords collectifs.
A16: Santé et sécurité : • les conditions de santé et de sécurité au travail ;
A17: • le bilan des accords signés avec les organisations syndicales ou les représentants du personnel en matière de santé et de sécurité au travail.
... A50: • la prise en compte dans la politique d'achat des enjeux sociaux et environnementaux.

Sheet NOTE 36
A4: 1-Code Forme Juridique (1) | D4: 3- Code Pays du Siège Social
A6: Société Anonyme (SA) à participation publique | B6: 0 | C6: 0
D7: Pays OHADA (²)
A8: Société Anonyme (SA) | B8: 0 | C8: 1
D9: Autres pays africains | E9: 2 | F9: 1
A10: Société à Responsabilité Limitée (SARL) | B10: 0 | C10: 2
D11: France | E11: 2 | F11: 3
A12: Société en Commandite Simple (SCS) | B12: 0 | C12: 3
D13: Autres pays de l’Union Européenne | E13: 3 | F13: 9
A14: Société en Nom Collectif (SNC) | B14: 0 | C14: 4
D15: U.S.A | E15: 4 | F15: 0
A16: Société en Participation (SP) | B16: 0 | C16: 5
D17: Canada | E17: 4 | F17: 1
A18: Groupement d’Intérêt Economique (GIE) | B18: 0 | C18: 6
D19: Autres pays américains | E19: 4 | F19: 9
A20: Association | B20: 0 | C20: 7
D21: Pays asiatiques | E21: 5 | F21: 0
A22: Société par Actions Simplifiées (SAS) | B22: 0 | C22: 8
D23: Autres pays | E23: 9 | F23: 9
A24: Autre Forme Juridique (à préciser) | B24: 0 | C24: 9
A27: 2- Code Régime Fiscal
A29: Réel Normal | C29: 1
A31: Réel simplifié | C31: 2
A33: Synthétique | C33: 3
A35: Forfait
A39: (1) Remplacer le premier 0 par 1 si l’entité bénéficie d’un agrément prioritaire
A40: (2) Bénin = 01 ; Burkina = 02 ; Côte d’ivoire = 03 ; Guinée Bissau = 04 ; Mali = 05 ; Niger = 06 ; Sénégal = 07 ; Togo = 08 ; Cameroun = 09 ; Congo = 10 ; Gabon = 11 ; République Centrafricaine = 12 ; Tchad = 13 ; Comores = 14 ; Guinée = 15 ; Guinée Equatoriale = 16 ; Congo RDC = 17.

Sheet CODES
A1: CODES ACTIVITES ECONOMIQIES
A2: Agriculture vivrière | C2: Industrie du caoutchouc et des plastiques
A3: 001 001 Culture Céréalière | C3: 022 001 Fabrication du caoutchouc naturel
A4: 001 002 Culture de tubercules et plantains | C4: 022 002 industries de caoutchouc
A5: 001 003 Culture de légumes | C5: 022 003 Fabrication de matières plastiques
A6: 001 004 Culture de condiments | C6: Fabrication d’autres produits minéraux non métallique et de matériaux de construction
A7: 001 005 Culture de fruits | C7: 023 001 Industrie du verre
A8: 001 006 Culture d’autres produits de l’agriculture vivrière | C8: 023 002 Fabrication de produits minéraux pour la construction
A9: Agriculture Industrielle et d’exportation | C9: 023 003 Fabrication d’autres produits minéraux non métalliques
A10: 002 001 Culture de canne à sucre | C10: Métallurgie et travail des métaux
A11: 002 002 Culture d’arachide d’huilerie | C11: 024 001 Métallurgie
A12: 002 003 Culture d’arachide de bouche | C12: 024 002 Travail des métaux
A13: 002 004 Culture de tabac | C13: Fabrication de machines, d’équipement et d’appareils électriques
... A82: 021 005 Fabrication d’autres produits chimiques | C82: 044 000 Correction territoriale
